package com.google.android.gms.internal;

import android.content.Context;
import android.util.DisplayMetrics;
import android.view.MotionEvent;
import dalvik.system.DexClassLoader;
import java.io.File;
import java.io.FileNotFoundException;
import java.io.FileOutputStream;
import java.io.IOException;
import java.io.UnsupportedEncodingException;
import java.lang.reflect.InvocationTargetException;
import java.lang.reflect.Method;
import java.nio.ByteBuffer;
import java.util.ArrayList;

public abstract class zzal
  extends zzak
{
  private static long startTime = 0L;
  private static Method zzmY;
  private static Method zzmZ;
  private static Method zzna;
  private static Method zznb;
  private static Method zznc;
  private static Method zznd;
  private static Method zzne;
  private static Method zznf;
  private static Method zzng;
  private static Method zznh;
  private static Method zzni;
  private static Method zznj;
  private static Method zznk;
  private static String zznl;
  private static String zznm;
  private static String zznn;
  private static zzar zzno;
  static boolean zznp = false;
  
  protected zzal(Context paramContext, zzap paramzzap, zzaq paramzzaq)
  {
    super(paramContext, paramzzap, paramzzaq);
  }
  
  static String zzU()
    throws zzal.zza
  {
    if (zznl == null) {
      throw new zza();
    }
    return zznl;
  }
  
  static Long zzV()
    throws zzal.zza
  {
    if (zzmY == null) {
      throw new zza();
    }
    try
    {
      Long localLong = (Long)zzmY.invoke(null, new Object[0]);
      return localLong;
    }
    catch (IllegalAccessException localIllegalAccessException)
    {
      throw new zza(localIllegalAccessException);
    }
    catch (InvocationTargetException localInvocationTargetException)
    {
      throw new zza(localInvocationTargetException);
    }
  }
  
  static String zzW()
    throws zzal.zza
  {
    if (zzna == null) {
      throw new zza();
    }
    try
    {
      String str = (String)zzna.invoke(null, new Object[0]);
      return str;
    }
    catch (IllegalAccessException localIllegalAccessException)
    {
      throw new zza(localIllegalAccessException);
    }
    catch (InvocationTargetException localInvocationTargetException)
    {
      throw new zza(localInvocationTargetException);
    }
  }
  
  static Long zzX()
    throws zzal.zza
  {
    if (zzmZ == null) {
      throw new zza();
    }
    try
    {
      Long localLong = (Long)zzmZ.invoke(null, new Object[0]);
      return localLong;
    }
    catch (IllegalAccessException localIllegalAccessException)
    {
      throw new zza(localIllegalAccessException);
    }
    catch (InvocationTargetException localInvocationTargetException)
    {
      throw new zza(localInvocationTargetException);
    }
  }
  
  static String zza(Context paramContext, zzap paramzzap)
    throws zzal.zza
  {
    String str;
    if (zznm != null) {
      str = zznm;
    }
    for (;;)
    {
      return str;
      if (zznb == null) {
        throw new zza();
      }
      try
      {
        Method localMethod = zznb;
        Object[] arrayOfObject = new Object[1];
        arrayOfObject[0] = paramContext;
        localByteBuffer = (ByteBuffer)localMethod.invoke(null, arrayOfObject);
        if (localByteBuffer == null) {
          throw new zza();
        }
      }
      catch (IllegalAccessException localIllegalAccessException)
      {
        ByteBuffer localByteBuffer;
        throw new zza(localIllegalAccessException);
        zznm = paramzzap.zza(localByteBuffer.array(), true);
        str = zznm;
      }
      catch (InvocationTargetException localInvocationTargetException)
      {
        throw new zza(localInvocationTargetException);
      }
    }
  }
  
  static ArrayList<Long> zza(MotionEvent paramMotionEvent, DisplayMetrics paramDisplayMetrics)
    throws zzal.zza
  {
    if ((zznc == null) || (paramMotionEvent == null)) {
      throw new zza();
    }
    try
    {
      Method localMethod = zznc;
      Object[] arrayOfObject = new Object[2];
      arrayOfObject[0] = paramMotionEvent;
      arrayOfObject[1] = paramDisplayMetrics;
      ArrayList localArrayList = (ArrayList)localMethod.invoke(null, arrayOfObject);
      return localArrayList;
    }
    catch (IllegalAccessException localIllegalAccessException)
    {
      throw new zza(localIllegalAccessException);
    }
    catch (InvocationTargetException localInvocationTargetException)
    {
      throw new zza(localInvocationTargetException);
    }
  }
  
  /* Error */
  /**
   * @deprecated
   */
  protected static void zza(String paramString, Context paramContext, zzap paramzzap)
  {
    // Byte code:
    //   0: ldc 2
    //   2: monitorenter
    //   3: getstatic 37	com/google/android/gms/internal/zzal:zznp	Z
    //   6: istore 4
    //   8: iload 4
    //   10: ifne +36 -> 46
    //   13: new 102	com/google/android/gms/internal/zzar
    //   16: dup
    //   17: aload_2
    //   18: aconst_null
    //   19: invokespecial 105	com/google/android/gms/internal/zzar:<init>	(Lcom/google/android/gms/internal/zzap;Ljava/security/SecureRandom;)V
    //   22: putstatic 107	com/google/android/gms/internal/zzal:zzno	Lcom/google/android/gms/internal/zzar;
    //   25: aload_0
    //   26: putstatic 45	com/google/android/gms/internal/zzal:zznl	Ljava/lang/String;
    //   29: aload_1
    //   30: invokestatic 111	com/google/android/gms/internal/zzal:zzl	(Landroid/content/Context;)V
    //   33: invokestatic 113	com/google/android/gms/internal/zzal:zzV	()Ljava/lang/Long;
    //   36: invokevirtual 117	java/lang/Long:longValue	()J
    //   39: putstatic 35	com/google/android/gms/internal/zzal:startTime	J
    //   42: iconst_1
    //   43: putstatic 37	com/google/android/gms/internal/zzal:zznp	Z
    //   46: ldc 2
    //   48: monitorexit
    //   49: return
    //   50: astore_3
    //   51: ldc 2
    //   53: monitorexit
    //   54: aload_3
    //   55: athrow
    //   56: astore 6
    //   58: goto -12 -> 46
    //   61: astore 5
    //   63: goto -17 -> 46
    // Local variable table:
    //   start	length	slot	name	signature
    //   0	66	0	paramString	String
    //   0	66	1	paramContext	Context
    //   0	66	2	paramzzap	zzap
    //   50	5	3	localObject	Object
    //   6	3	4	bool	boolean
    //   61	1	5	localzza	zza
    //   56	1	6	localUnsupportedOperationException	UnsupportedOperationException
    // Exception table:
    //   from	to	target	type
    //   3	8	50	finally
    //   13	46	50	finally
    //   13	46	56	java/lang/UnsupportedOperationException
    //   13	46	61	com/google/android/gms/internal/zzal$zza
  }
  
  static String zzb(Context paramContext, zzap paramzzap)
    throws zzal.zza
  {
    String str;
    if (zznn != null) {
      str = zznn;
    }
    for (;;)
    {
      return str;
      if (zzne == null) {
        throw new zza();
      }
      try
      {
        Method localMethod = zzne;
        Object[] arrayOfObject = new Object[1];
        arrayOfObject[0] = paramContext;
        localByteBuffer = (ByteBuffer)localMethod.invoke(null, arrayOfObject);
        if (localByteBuffer == null) {
          throw new zza();
        }
      }
      catch (IllegalAccessException localIllegalAccessException)
      {
        ByteBuffer localByteBuffer;
        throw new zza(localIllegalAccessException);
        zznn = paramzzap.zza(localByteBuffer.array(), true);
        str = zznn;
      }
      catch (InvocationTargetException localInvocationTargetException)
      {
        throw new zza(localInvocationTargetException);
      }
    }
  }
  
  private static String zzb(byte[] paramArrayOfByte, String paramString)
    throws zzal.zza
  {
    try
    {
      String str = new String(zzno.zzc(paramArrayOfByte, paramString), "UTF-8");
      return str;
    }
    catch (zzar.zza localzza)
    {
      throw new zza(localzza);
    }
    catch (UnsupportedEncodingException localUnsupportedEncodingException)
    {
      throw new zza(localUnsupportedEncodingException);
    }
  }
  
  static String zze(Context paramContext)
    throws zzal.zza
  {
    if (zznd == null) {
      throw new zza();
    }
    String str;
    try
    {
      Method localMethod = zznd;
      Object[] arrayOfObject = new Object[1];
      arrayOfObject[0] = paramContext;
      str = (String)localMethod.invoke(null, arrayOfObject);
      if (str == null) {
        throw new zza();
      }
    }
    catch (IllegalAccessException localIllegalAccessException)
    {
      throw new zza(localIllegalAccessException);
    }
    catch (InvocationTargetException localInvocationTargetException)
    {
      throw new zza(localInvocationTargetException);
    }
    return str;
  }
  
  static String zzf(Context paramContext)
    throws zzal.zza
  {
    if (zznh == null) {
      throw new zza();
    }
    try
    {
      Method localMethod = zznh;
      Object[] arrayOfObject = new Object[1];
      arrayOfObject[0] = paramContext;
      String str = (String)localMethod.invoke(null, arrayOfObject);
      return str;
    }
    catch (IllegalAccessException localIllegalAccessException)
    {
      throw new zza(localIllegalAccessException);
    }
    catch (InvocationTargetException localInvocationTargetException)
    {
      throw new zza(localInvocationTargetException);
    }
  }
  
  static Long zzg(Context paramContext)
    throws zzal.zza
  {
    if (zzni == null) {
      throw new zza();
    }
    try
    {
      Method localMethod = zzni;
      Object[] arrayOfObject = new Object[1];
      arrayOfObject[0] = paramContext;
      Long localLong = (Long)localMethod.invoke(null, arrayOfObject);
      return localLong;
    }
    catch (IllegalAccessException localIllegalAccessException)
    {
      throw new zza(localIllegalAccessException);
    }
    catch (InvocationTargetException localInvocationTargetException)
    {
      throw new zza(localInvocationTargetException);
    }
  }
  
  static ArrayList<Long> zzh(Context paramContext)
    throws zzal.zza
  {
    if (zznf == null) {
      throw new zza();
    }
    ArrayList localArrayList;
    try
    {
      Method localMethod = zznf;
      Object[] arrayOfObject = new Object[1];
      arrayOfObject[0] = paramContext;
      localArrayList = (ArrayList)localMethod.invoke(null, arrayOfObject);
      if ((localArrayList == null) || (localArrayList.size() != 2)) {
        throw new zza();
      }
    }
    catch (IllegalAccessException localIllegalAccessException)
    {
      throw new zza(localIllegalAccessException);
    }
    catch (InvocationTargetException localInvocationTargetException)
    {
      throw new zza(localInvocationTargetException);
    }
    return localArrayList;
  }
  
  static int[] zzi(Context paramContext)
    throws zzal.zza
  {
    if (zzng == null) {
      throw new zza();
    }
    try
    {
      Method localMethod = zzng;
      Object[] arrayOfObject = new Object[1];
      arrayOfObject[0] = paramContext;
      int[] arrayOfInt = (int[])localMethod.invoke(null, arrayOfObject);
      return arrayOfInt;
    }
    catch (IllegalAccessException localIllegalAccessException)
    {
      throw new zza(localIllegalAccessException);
    }
    catch (InvocationTargetException localInvocationTargetException)
    {
      throw new zza(localInvocationTargetException);
    }
  }
  
  static int zzj(Context paramContext)
    throws zzal.zza
  {
    if (zznj == null) {
      throw new zza();
    }
    try
    {
      Method localMethod = zznj;
      Object[] arrayOfObject = new Object[1];
      arrayOfObject[0] = paramContext;
      int i = ((Integer)localMethod.invoke(null, arrayOfObject)).intValue();
      return i;
    }
    catch (IllegalAccessException localIllegalAccessException)
    {
      throw new zza(localIllegalAccessException);
    }
    catch (InvocationTargetException localInvocationTargetException)
    {
      throw new zza(localInvocationTargetException);
    }
  }
  
  static int zzk(Context paramContext)
    throws zzal.zza
  {
    if (zznk == null) {
      throw new zza();
    }
    try
    {
      Method localMethod = zznk;
      Object[] arrayOfObject = new Object[1];
      arrayOfObject[0] = paramContext;
      int i = ((Integer)localMethod.invoke(null, arrayOfObject)).intValue();
      return i;
    }
    catch (IllegalAccessException localIllegalAccessException)
    {
      throw new zza(localIllegalAccessException);
    }
    catch (InvocationTargetException localInvocationTargetException)
    {
      throw new zza(localInvocationTargetException);
    }
  }
  
  private static void zzl(Context paramContext)
    throws zzal.zza
  {
    try
    {
      arrayOfByte1 = zzno.zzl(zzat.getKey());
      arrayOfByte2 = zzno.zzc(arrayOfByte1, zzat.zzad());
      localFile1 = paramContext.getCacheDir();
      if (localFile1 == null)
      {
        localFile1 = paramContext.getDir("dex", 0);
        if (localFile1 == null) {
          throw new zza();
        }
      }
    }
    catch (FileNotFoundException localFileNotFoundException)
    {
      byte[] arrayOfByte1;
      byte[] arrayOfByte2;
      File localFile1;
      throw new zza(localFileNotFoundException);
      File localFile2 = localFile1;
      File localFile3 = File.createTempFile("ads", ".jar", localFile2);
      FileOutputStream localFileOutputStream = new FileOutputStream(localFile3);
      localFileOutputStream.write(arrayOfByte2, 0, arrayOfByte2.length);
      localFileOutputStream.close();
      try
      {
        DexClassLoader localDexClassLoader = new DexClassLoader(localFile3.getAbsolutePath(), localFile2.getAbsolutePath(), null, paramContext.getClassLoader());
        Class localClass1 = localDexClassLoader.loadClass(zzb(arrayOfByte1, zzat.zzam()));
        Class localClass2 = localDexClassLoader.loadClass(zzb(arrayOfByte1, zzat.zzaA()));
        Class localClass3 = localDexClassLoader.loadClass(zzb(arrayOfByte1, zzat.zzau()));
        Class localClass4 = localDexClassLoader.loadClass(zzb(arrayOfByte1, zzat.zzaq()));
        Class localClass5 = localDexClassLoader.loadClass(zzb(arrayOfByte1, zzat.zzaC()));
        Class localClass6 = localDexClassLoader.loadClass(zzb(arrayOfByte1, zzat.zzao()));
        Class localClass7 = localDexClassLoader.loadClass(zzb(arrayOfByte1, zzat.zzay()));
        Class localClass8 = localDexClassLoader.loadClass(zzb(arrayOfByte1, zzat.zzaw()));
        Class localClass9 = localDexClassLoader.loadClass(zzb(arrayOfByte1, zzat.zzak()));
        Class localClass10 = localDexClassLoader.loadClass(zzb(arrayOfByte1, zzat.zzai()));
        Class localClass11 = localDexClassLoader.loadClass(zzb(arrayOfByte1, zzat.zzag()));
        Class localClass12 = localDexClassLoader.loadClass(zzb(arrayOfByte1, zzat.zzas()));
        Class localClass13 = localDexClassLoader.loadClass(zzb(arrayOfByte1, zzat.zzae()));
        zzmY = localClass1.getMethod(zzb(arrayOfByte1, zzat.zzan()), new Class[0]);
        zzmZ = localClass2.getMethod(zzb(arrayOfByte1, zzat.zzaB()), new Class[0]);
        zzna = localClass3.getMethod(zzb(arrayOfByte1, zzat.zzav()), new Class[0]);
        String str2 = zzb(arrayOfByte1, zzat.zzar());
        Class[] arrayOfClass1 = new Class[1];
        arrayOfClass1[0] = Context.class;
        zznb = localClass4.getMethod(str2, arrayOfClass1);
        String str3 = zzb(arrayOfByte1, zzat.zzaD());
        Class[] arrayOfClass2 = new Class[2];
        arrayOfClass2[0] = MotionEvent.class;
        arrayOfClass2[1] = DisplayMetrics.class;
        zznc = localClass5.getMethod(str3, arrayOfClass2);
        String str4 = zzb(arrayOfByte1, zzat.zzap());
        Class[] arrayOfClass3 = new Class[1];
        arrayOfClass3[0] = Context.class;
        zznd = localClass6.getMethod(str4, arrayOfClass3);
        String str5 = zzb(arrayOfByte1, zzat.zzaz());
        Class[] arrayOfClass4 = new Class[1];
        arrayOfClass4[0] = Context.class;
        zzne = localClass7.getMethod(str5, arrayOfClass4);
        String str6 = zzb(arrayOfByte1, zzat.zzax());
        Class[] arrayOfClass5 = new Class[1];
        arrayOfClass5[0] = Context.class;
        zznf = localClass8.getMethod(str6, arrayOfClass5);
        String str7 = zzb(arrayOfByte1, zzat.zzal());
        Class[] arrayOfClass6 = new Class[1];
        arrayOfClass6[0] = Context.class;
        zzng = localClass9.getMethod(str7, arrayOfClass6);
        String str8 = zzb(arrayOfByte1, zzat.zzaj());
        Class[] arrayOfClass7 = new Class[1];
        arrayOfClass7[0] = Context.class;
        zznh = localClass10.getMethod(str8, arrayOfClass7);
        String str9 = zzb(arrayOfByte1, zzat.zzah());
        Class[] arrayOfClass8 = new Class[1];
        arrayOfClass8[0] = Context.class;
        zzni = localClass11.getMethod(str9, arrayOfClass8);
        String str10 = zzb(arrayOfByte1, zzat.zzat());
        Class[] arrayOfClass9 = new Class[1];
        arrayOfClass9[0] = Context.class;
        zznj = localClass12.getMethod(str10, arrayOfClass9);
        String str11 = zzb(arrayOfByte1, zzat.zzaf());
        Class[] arrayOfClass10 = new Class[1];
        arrayOfClass10[0] = Context.class;
        zznk = localClass13.getMethod(str11, arrayOfClass10);
        String str12;
        return;
      }
      finally
      {
        String str1 = localFile3.getName();
        localFile3.delete();
        new File(localFile2, str1.replace(".jar", ".dex")).delete();
      }
    }
    catch (IOException localIOException)
    {
      throw new zza(localIOException);
    }
    catch (ClassNotFoundException localClassNotFoundException)
    {
      throw new zza(localClassNotFoundException);
    }
    catch (zzar.zza localzza)
    {
      throw new zza(localzza);
    }
    catch (NoSuchMethodException localNoSuchMethodException)
    {
      throw new zza(localNoSuchMethodException);
    }
    catch (NullPointerException localNullPointerException)
    {
      throw new zza(localNullPointerException);
    }
  }
  
  /* Error */
  protected void zzc(Context paramContext)
  {
    // Byte code:
    //   0: aload_0
    //   1: iconst_1
    //   2: invokestatic 352	com/google/android/gms/internal/zzal:zzW	()Ljava/lang/String;
    //   5: invokevirtual 355	com/google/android/gms/internal/zzal:zza	(ILjava/lang/String;)V
    //   8: aload_0
    //   9: iconst_2
    //   10: invokestatic 357	com/google/android/gms/internal/zzal:zzU	()Ljava/lang/String;
    //   13: invokevirtual 355	com/google/android/gms/internal/zzal:zza	(ILjava/lang/String;)V
    //   16: invokestatic 113	com/google/android/gms/internal/zzal:zzV	()Ljava/lang/Long;
    //   19: invokevirtual 117	java/lang/Long:longValue	()J
    //   22: lstore 17
    //   24: aload_0
    //   25: bipush 25
    //   27: lload 17
    //   29: invokevirtual 360	com/google/android/gms/internal/zzal:zza	(IJ)V
    //   32: getstatic 35	com/google/android/gms/internal/zzal:startTime	J
    //   35: lconst_0
    //   36: lcmp
    //   37: ifeq +24 -> 61
    //   40: aload_0
    //   41: bipush 17
    //   43: lload 17
    //   45: getstatic 35	com/google/android/gms/internal/zzal:startTime	J
    //   48: lsub
    //   49: invokevirtual 360	com/google/android/gms/internal/zzal:zza	(IJ)V
    //   52: aload_0
    //   53: bipush 23
    //   55: getstatic 35	com/google/android/gms/internal/zzal:startTime	J
    //   58: invokevirtual 360	com/google/android/gms/internal/zzal:zza	(IJ)V
    //   61: aload_1
    //   62: invokestatic 362	com/google/android/gms/internal/zzal:zzh	(Landroid/content/Context;)Ljava/util/ArrayList;
    //   65: astore 16
    //   67: aload_0
    //   68: bipush 31
    //   70: aload 16
    //   72: iconst_0
    //   73: invokevirtual 366	java/util/ArrayList:get	(I)Ljava/lang/Object;
    //   76: checkcast 65	java/lang/Long
    //   79: invokevirtual 117	java/lang/Long:longValue	()J
    //   82: invokevirtual 360	com/google/android/gms/internal/zzal:zza	(IJ)V
    //   85: aload_0
    //   86: bipush 32
    //   88: aload 16
    //   90: iconst_1
    //   91: invokevirtual 366	java/util/ArrayList:get	(I)Ljava/lang/Object;
    //   94: checkcast 65	java/lang/Long
    //   97: invokevirtual 117	java/lang/Long:longValue	()J
    //   100: invokevirtual 360	com/google/android/gms/internal/zzal:zza	(IJ)V
    //   103: aload_0
    //   104: bipush 33
    //   106: invokestatic 368	com/google/android/gms/internal/zzal:zzX	()Ljava/lang/Long;
    //   109: invokevirtual 117	java/lang/Long:longValue	()J
    //   112: invokevirtual 360	com/google/android/gms/internal/zzal:zza	(IJ)V
    //   115: aload_0
    //   116: bipush 27
    //   118: aload_1
    //   119: aload_0
    //   120: getfield 372	com/google/android/gms/internal/zzal:zzmW	Lcom/google/android/gms/internal/zzap;
    //   123: invokestatic 374	com/google/android/gms/internal/zzal:zza	(Landroid/content/Context;Lcom/google/android/gms/internal/zzap;)Ljava/lang/String;
    //   126: invokevirtual 355	com/google/android/gms/internal/zzal:zza	(ILjava/lang/String;)V
    //   129: aload_0
    //   130: bipush 29
    //   132: aload_1
    //   133: aload_0
    //   134: getfield 372	com/google/android/gms/internal/zzal:zzmW	Lcom/google/android/gms/internal/zzap;
    //   137: invokestatic 376	com/google/android/gms/internal/zzal:zzb	(Landroid/content/Context;Lcom/google/android/gms/internal/zzap;)Ljava/lang/String;
    //   140: invokevirtual 355	com/google/android/gms/internal/zzal:zza	(ILjava/lang/String;)V
    //   143: aload_1
    //   144: invokestatic 378	com/google/android/gms/internal/zzal:zzi	(Landroid/content/Context;)[I
    //   147: astore 15
    //   149: aload_0
    //   150: iconst_5
    //   151: aload 15
    //   153: iconst_0
    //   154: iaload
    //   155: i2l
    //   156: invokevirtual 360	com/google/android/gms/internal/zzal:zza	(IJ)V
    //   159: aload_0
    //   160: bipush 6
    //   162: aload 15
    //   164: iconst_1
    //   165: iaload
    //   166: i2l
    //   167: invokevirtual 360	com/google/android/gms/internal/zzal:zza	(IJ)V
    //   170: aload_0
    //   171: bipush 12
    //   173: aload_1
    //   174: invokestatic 380	com/google/android/gms/internal/zzal:zzj	(Landroid/content/Context;)I
    //   177: i2l
    //   178: invokevirtual 360	com/google/android/gms/internal/zzal:zza	(IJ)V
    //   181: aload_0
    //   182: iconst_3
    //   183: aload_1
    //   184: invokestatic 382	com/google/android/gms/internal/zzal:zzk	(Landroid/content/Context;)I
    //   187: i2l
    //   188: invokevirtual 360	com/google/android/gms/internal/zzal:zza	(IJ)V
    //   191: aload_0
    //   192: bipush 34
    //   194: aload_1
    //   195: invokestatic 384	com/google/android/gms/internal/zzal:zzf	(Landroid/content/Context;)Ljava/lang/String;
    //   198: invokevirtual 355	com/google/android/gms/internal/zzal:zza	(ILjava/lang/String;)V
    //   201: aload_0
    //   202: bipush 35
    //   204: aload_1
    //   205: invokestatic 386	com/google/android/gms/internal/zzal:zzg	(Landroid/content/Context;)Ljava/lang/Long;
    //   208: invokevirtual 117	java/lang/Long:longValue	()J
    //   211: invokevirtual 360	com/google/android/gms/internal/zzal:zza	(IJ)V
    //   214: return
    //   215: astore 14
    //   217: goto -3 -> 214
    //   220: astore 13
    //   222: goto -8 -> 214
    //   225: astore 12
    //   227: goto -26 -> 201
    //   230: astore 11
    //   232: goto -41 -> 191
    //   235: astore 10
    //   237: goto -56 -> 181
    //   240: astore 9
    //   242: goto -72 -> 170
    //   245: astore 8
    //   247: goto -104 -> 143
    //   250: astore 7
    //   252: goto -123 -> 129
    //   255: astore 6
    //   257: goto -142 -> 115
    //   260: astore 5
    //   262: goto -159 -> 103
    //   265: astore 4
    //   267: goto -206 -> 61
    //   270: astore_3
    //   271: goto -255 -> 16
    //   274: astore_2
    //   275: goto -267 -> 8
    // Local variable table:
    //   start	length	slot	name	signature
    //   0	278	0	this	zzal
    //   0	278	1	paramContext	Context
    //   274	1	2	localzza1	zza
    //   270	1	3	localzza2	zza
    //   265	1	4	localzza3	zza
    //   260	1	5	localzza4	zza
    //   255	1	6	localzza5	zza
    //   250	1	7	localzza6	zza
    //   245	1	8	localzza7	zza
    //   240	1	9	localzza8	zza
    //   235	1	10	localzza9	zza
    //   230	1	11	localzza10	zza
    //   225	1	12	localzza11	zza
    //   220	1	13	localzza12	zza
    //   215	1	14	localIOException	IOException
    //   147	16	15	arrayOfInt	int[]
    //   65	24	16	localArrayList	ArrayList
    //   22	22	17	l	long
    // Exception table:
    //   from	to	target	type
    //   0	8	215	java/io/IOException
    //   8	16	215	java/io/IOException
    //   16	61	215	java/io/IOException
    //   61	103	215	java/io/IOException
    //   103	115	215	java/io/IOException
    //   115	129	215	java/io/IOException
    //   129	143	215	java/io/IOException
    //   143	170	215	java/io/IOException
    //   170	181	215	java/io/IOException
    //   181	191	215	java/io/IOException
    //   191	201	215	java/io/IOException
    //   201	214	215	java/io/IOException
    //   201	214	220	com/google/android/gms/internal/zzal$zza
    //   191	201	225	com/google/android/gms/internal/zzal$zza
    //   181	191	230	com/google/android/gms/internal/zzal$zza
    //   170	181	235	com/google/android/gms/internal/zzal$zza
    //   143	170	240	com/google/android/gms/internal/zzal$zza
    //   129	143	245	com/google/android/gms/internal/zzal$zza
    //   115	129	250	com/google/android/gms/internal/zzal$zza
    //   103	115	255	com/google/android/gms/internal/zzal$zza
    //   61	103	260	com/google/android/gms/internal/zzal$zza
    //   16	61	265	com/google/android/gms/internal/zzal$zza
    //   8	16	270	com/google/android/gms/internal/zzal$zza
    //   0	8	274	com/google/android/gms/internal/zzal$zza
  }
  
  /* Error */
  protected void zzd(Context paramContext)
  {
    // Byte code:
    //   0: aload_0
    //   1: iconst_2
    //   2: invokestatic 357	com/google/android/gms/internal/zzal:zzU	()Ljava/lang/String;
    //   5: invokevirtual 355	com/google/android/gms/internal/zzal:zza	(ILjava/lang/String;)V
    //   8: aload_0
    //   9: iconst_1
    //   10: invokestatic 352	com/google/android/gms/internal/zzal:zzW	()Ljava/lang/String;
    //   13: invokevirtual 355	com/google/android/gms/internal/zzal:zza	(ILjava/lang/String;)V
    //   16: aload_0
    //   17: bipush 25
    //   19: invokestatic 113	com/google/android/gms/internal/zzal:zzV	()Ljava/lang/Long;
    //   22: invokevirtual 117	java/lang/Long:longValue	()J
    //   25: invokevirtual 360	com/google/android/gms/internal/zzal:zza	(IJ)V
    //   28: aload_0
    //   29: getfield 391	com/google/android/gms/internal/zzal:zzmU	Landroid/view/MotionEvent;
    //   32: aload_0
    //   33: getfield 395	com/google/android/gms/internal/zzal:zzmV	Landroid/util/DisplayMetrics;
    //   36: invokestatic 397	com/google/android/gms/internal/zzal:zza	(Landroid/view/MotionEvent;Landroid/util/DisplayMetrics;)Ljava/util/ArrayList;
    //   39: astore 9
    //   41: aload_0
    //   42: bipush 14
    //   44: aload 9
    //   46: iconst_0
    //   47: invokevirtual 366	java/util/ArrayList:get	(I)Ljava/lang/Object;
    //   50: checkcast 65	java/lang/Long
    //   53: invokevirtual 117	java/lang/Long:longValue	()J
    //   56: invokevirtual 360	com/google/android/gms/internal/zzal:zza	(IJ)V
    //   59: aload_0
    //   60: bipush 15
    //   62: aload 9
    //   64: iconst_1
    //   65: invokevirtual 366	java/util/ArrayList:get	(I)Ljava/lang/Object;
    //   68: checkcast 65	java/lang/Long
    //   71: invokevirtual 117	java/lang/Long:longValue	()J
    //   74: invokevirtual 360	com/google/android/gms/internal/zzal:zza	(IJ)V
    //   77: aload 9
    //   79: invokevirtual 155	java/util/ArrayList:size	()I
    //   82: iconst_3
    //   83: if_icmplt +21 -> 104
    //   86: aload_0
    //   87: bipush 16
    //   89: aload 9
    //   91: iconst_2
    //   92: invokevirtual 366	java/util/ArrayList:get	(I)Ljava/lang/Object;
    //   95: checkcast 65	java/lang/Long
    //   98: invokevirtual 117	java/lang/Long:longValue	()J
    //   101: invokevirtual 360	com/google/android/gms/internal/zzal:zza	(IJ)V
    //   104: aload_0
    //   105: bipush 34
    //   107: aload_1
    //   108: invokestatic 384	com/google/android/gms/internal/zzal:zzf	(Landroid/content/Context;)Ljava/lang/String;
    //   111: invokevirtual 355	com/google/android/gms/internal/zzal:zza	(ILjava/lang/String;)V
    //   114: aload_0
    //   115: bipush 35
    //   117: aload_1
    //   118: invokestatic 386	com/google/android/gms/internal/zzal:zzg	(Landroid/content/Context;)Ljava/lang/Long;
    //   121: invokevirtual 117	java/lang/Long:longValue	()J
    //   124: invokevirtual 360	com/google/android/gms/internal/zzal:zza	(IJ)V
    //   127: return
    //   128: astore 8
    //   130: goto -3 -> 127
    //   133: astore 7
    //   135: goto -8 -> 127
    //   138: astore 6
    //   140: goto -26 -> 114
    //   143: astore 5
    //   145: goto -41 -> 104
    //   148: astore 4
    //   150: goto -122 -> 28
    //   153: astore_3
    //   154: goto -138 -> 16
    //   157: astore_2
    //   158: goto -150 -> 8
    // Local variable table:
    //   start	length	slot	name	signature
    //   0	161	0	this	zzal
    //   0	161	1	paramContext	Context
    //   157	1	2	localzza1	zza
    //   153	1	3	localzza2	zza
    //   148	1	4	localzza3	zza
    //   143	1	5	localzza4	zza
    //   138	1	6	localzza5	zza
    //   133	1	7	localzza6	zza
    //   128	1	8	localIOException	IOException
    //   39	51	9	localArrayList	ArrayList
    // Exception table:
    //   from	to	target	type
    //   0	8	128	java/io/IOException
    //   8	16	128	java/io/IOException
    //   16	28	128	java/io/IOException
    //   28	104	128	java/io/IOException
    //   104	114	128	java/io/IOException
    //   114	127	128	java/io/IOException
    //   114	127	133	com/google/android/gms/internal/zzal$zza
    //   104	114	138	com/google/android/gms/internal/zzal$zza
    //   28	104	143	com/google/android/gms/internal/zzal$zza
    //   16	28	148	com/google/android/gms/internal/zzal$zza
    //   8	16	153	com/google/android/gms/internal/zzal$zza
    //   0	8	157	com/google/android/gms/internal/zzal$zza
  }
  
  static class zza
    extends Exception
  {
    public zza() {}
    
    public zza(Throwable paramThrowable)
    {
      super();
    }
  }
}


/* Location:              /Users/tjledwith/Downloads/dex2jar-0.0.9.8/classes_dex2jar.jar!/com/google/android/gms/internal/zzal.class
 * Java compiler version: 6 (50.0)
 * JD-Core Version:       0.7.1
 */