package com.google.android.gms.internal;

import android.os.Binder;
import android.os.Bundle;
import android.os.IBinder;
import android.os.IInterface;
import android.os.Parcel;
import android.os.RemoteException;
import com.google.android.gms.ads.internal.client.AdRequestParcel;
import com.google.android.gms.ads.internal.client.AdSizeParcel;
import com.google.android.gms.ads.internal.client.zzg;
import com.google.android.gms.ads.internal.formats.NativeAdOptionsParcel;
import com.google.android.gms.ads.internal.reward.mediation.client.zza;
import com.google.android.gms.ads.internal.reward.mediation.client.zza.zza;
import com.google.android.gms.dynamic.zzd;
import com.google.android.gms.dynamic.zzd.zza;
import java.util.List;

public abstract interface zzen
  extends IInterface
{
  public abstract void destroy()
    throws RemoteException;
  
  public abstract zzd getView()
    throws RemoteException;
  
  public abstract boolean isInitialized()
    throws RemoteException;
  
  public abstract void pause()
    throws RemoteException;
  
  public abstract void resume()
    throws RemoteException;
  
  public abstract void showInterstitial()
    throws RemoteException;
  
  public abstract void showVideo()
    throws RemoteException;
  
  public abstract void zza(AdRequestParcel paramAdRequestParcel, String paramString)
    throws RemoteException;
  
  public abstract void zza(zzd paramzzd, AdRequestParcel paramAdRequestParcel, String paramString1, zza paramzza, String paramString2)
    throws RemoteException;
  
  public abstract void zza(zzd paramzzd, AdRequestParcel paramAdRequestParcel, String paramString, zzeo paramzzeo)
    throws RemoteException;
  
  public abstract void zza(zzd paramzzd, AdRequestParcel paramAdRequestParcel, String paramString1, String paramString2, zzeo paramzzeo)
    throws RemoteException;
  
  public abstract void zza(zzd paramzzd, AdRequestParcel paramAdRequestParcel, String paramString1, String paramString2, zzeo paramzzeo, NativeAdOptionsParcel paramNativeAdOptionsParcel, List<String> paramList)
    throws RemoteException;
  
  public abstract void zza(zzd paramzzd, AdSizeParcel paramAdSizeParcel, AdRequestParcel paramAdRequestParcel, String paramString, zzeo paramzzeo)
    throws RemoteException;
  
  public abstract void zza(zzd paramzzd, AdSizeParcel paramAdSizeParcel, AdRequestParcel paramAdRequestParcel, String paramString1, String paramString2, zzeo paramzzeo)
    throws RemoteException;
  
  public abstract zzeq zzdV()
    throws RemoteException;
  
  public abstract zzer zzdW()
    throws RemoteException;
  
  public abstract Bundle zzdX()
    throws RemoteException;
  
  public abstract Bundle zzdY()
    throws RemoteException;
  
  public abstract Bundle zzdZ()
    throws RemoteException;
  
  public static abstract class zza
    extends Binder
    implements zzen
  {
    public zza()
    {
      attachInterface(this, "com.google.android.gms.ads.internal.mediation.client.IMediationAdapter");
    }
    
    public static zzen zzF(IBinder paramIBinder)
    {
      Object localObject;
      if (paramIBinder == null) {
        localObject = null;
      }
      for (;;)
      {
        return (zzen)localObject;
        IInterface localIInterface = paramIBinder.queryLocalInterface("com.google.android.gms.ads.internal.mediation.client.IMediationAdapter");
        if ((localIInterface != null) && ((localIInterface instanceof zzen))) {
          localObject = (zzen)localIInterface;
        } else {
          localObject = new zza(paramIBinder);
        }
      }
    }
    
    public IBinder asBinder()
    {
      return this;
    }
    
    public boolean onTransact(int paramInt1, Parcel paramParcel1, Parcel paramParcel2, int paramInt2)
      throws RemoteException
    {
      Object localObject = null;
      int i = 1;
      switch (paramInt1)
      {
      default: 
        i = super.onTransact(paramInt1, paramParcel1, paramParcel2, paramInt2);
      }
      for (;;)
      {
        return i;
        paramParcel2.writeString("com.google.android.gms.ads.internal.mediation.client.IMediationAdapter");
        continue;
        paramParcel1.enforceInterface("com.google.android.gms.ads.internal.mediation.client.IMediationAdapter");
        zzd localzzd7 = zzd.zza.zzbk(paramParcel1.readStrongBinder());
        AdSizeParcel localAdSizeParcel2;
        if (paramParcel1.readInt() != 0)
        {
          localAdSizeParcel2 = AdSizeParcel.CREATOR.zzc(paramParcel1);
          label230:
          if (paramParcel1.readInt() == 0) {
            break label280;
          }
        }
        label280:
        for (AdRequestParcel localAdRequestParcel5 = AdRequestParcel.CREATOR.zzb(paramParcel1);; localAdRequestParcel5 = null)
        {
          zza(localzzd7, localAdSizeParcel2, localAdRequestParcel5, paramParcel1.readString(), zzeo.zza.zzG(paramParcel1.readStrongBinder()));
          paramParcel2.writeNoException();
          break;
          localAdSizeParcel2 = null;
          break label230;
        }
        paramParcel1.enforceInterface("com.google.android.gms.ads.internal.mediation.client.IMediationAdapter");
        zzd localzzd6 = getView();
        paramParcel2.writeNoException();
        if (localzzd6 != null) {
          localObject = localzzd6.asBinder();
        }
        paramParcel2.writeStrongBinder((IBinder)localObject);
        continue;
        paramParcel1.enforceInterface("com.google.android.gms.ads.internal.mediation.client.IMediationAdapter");
        zzd localzzd5 = zzd.zza.zzbk(paramParcel1.readStrongBinder());
        if (paramParcel1.readInt() != 0) {
          localObject = AdRequestParcel.CREATOR.zzb(paramParcel1);
        }
        zza(localzzd5, (AdRequestParcel)localObject, paramParcel1.readString(), zzeo.zza.zzG(paramParcel1.readStrongBinder()));
        paramParcel2.writeNoException();
        continue;
        paramParcel1.enforceInterface("com.google.android.gms.ads.internal.mediation.client.IMediationAdapter");
        showInterstitial();
        paramParcel2.writeNoException();
        continue;
        paramParcel1.enforceInterface("com.google.android.gms.ads.internal.mediation.client.IMediationAdapter");
        destroy();
        paramParcel2.writeNoException();
        continue;
        paramParcel1.enforceInterface("com.google.android.gms.ads.internal.mediation.client.IMediationAdapter");
        zzd localzzd4 = zzd.zza.zzbk(paramParcel1.readStrongBinder());
        AdSizeParcel localAdSizeParcel1;
        if (paramParcel1.readInt() != 0)
        {
          localAdSizeParcel1 = AdSizeParcel.CREATOR.zzc(paramParcel1);
          label447:
          if (paramParcel1.readInt() == 0) {
            break label501;
          }
        }
        label501:
        for (AdRequestParcel localAdRequestParcel4 = AdRequestParcel.CREATOR.zzb(paramParcel1);; localAdRequestParcel4 = null)
        {
          zza(localzzd4, localAdSizeParcel1, localAdRequestParcel4, paramParcel1.readString(), paramParcel1.readString(), zzeo.zza.zzG(paramParcel1.readStrongBinder()));
          paramParcel2.writeNoException();
          break;
          localAdSizeParcel1 = null;
          break label447;
        }
        paramParcel1.enforceInterface("com.google.android.gms.ads.internal.mediation.client.IMediationAdapter");
        zzd localzzd3 = zzd.zza.zzbk(paramParcel1.readStrongBinder());
        if (paramParcel1.readInt() != 0) {}
        for (AdRequestParcel localAdRequestParcel3 = AdRequestParcel.CREATOR.zzb(paramParcel1);; localAdRequestParcel3 = null)
        {
          zza(localzzd3, localAdRequestParcel3, paramParcel1.readString(), paramParcel1.readString(), zzeo.zza.zzG(paramParcel1.readStrongBinder()));
          paramParcel2.writeNoException();
          break;
        }
        paramParcel1.enforceInterface("com.google.android.gms.ads.internal.mediation.client.IMediationAdapter");
        pause();
        paramParcel2.writeNoException();
        continue;
        paramParcel1.enforceInterface("com.google.android.gms.ads.internal.mediation.client.IMediationAdapter");
        resume();
        paramParcel2.writeNoException();
        continue;
        paramParcel1.enforceInterface("com.google.android.gms.ads.internal.mediation.client.IMediationAdapter");
        zzd localzzd2 = zzd.zza.zzbk(paramParcel1.readStrongBinder());
        if (paramParcel1.readInt() != 0) {}
        for (AdRequestParcel localAdRequestParcel2 = AdRequestParcel.CREATOR.zzb(paramParcel1);; localAdRequestParcel2 = null)
        {
          zza(localzzd2, localAdRequestParcel2, paramParcel1.readString(), zza.zza.zzae(paramParcel1.readStrongBinder()), paramParcel1.readString());
          paramParcel2.writeNoException();
          break;
        }
        paramParcel1.enforceInterface("com.google.android.gms.ads.internal.mediation.client.IMediationAdapter");
        if (paramParcel1.readInt() != 0) {
          localObject = AdRequestParcel.CREATOR.zzb(paramParcel1);
        }
        zza((AdRequestParcel)localObject, paramParcel1.readString());
        paramParcel2.writeNoException();
        continue;
        paramParcel1.enforceInterface("com.google.android.gms.ads.internal.mediation.client.IMediationAdapter");
        showVideo();
        paramParcel2.writeNoException();
        continue;
        paramParcel1.enforceInterface("com.google.android.gms.ads.internal.mediation.client.IMediationAdapter");
        boolean bool = isInitialized();
        paramParcel2.writeNoException();
        if (bool) {}
        int k;
        for (int j = i;; k = 0)
        {
          paramParcel2.writeInt(j);
          break;
        }
        paramParcel1.enforceInterface("com.google.android.gms.ads.internal.mediation.client.IMediationAdapter");
        zzd localzzd1 = zzd.zza.zzbk(paramParcel1.readStrongBinder());
        AdRequestParcel localAdRequestParcel1;
        label802:
        String str1;
        String str2;
        zzeo localzzeo;
        if (paramParcel1.readInt() != 0)
        {
          localAdRequestParcel1 = AdRequestParcel.CREATOR.zzb(paramParcel1);
          str1 = paramParcel1.readString();
          str2 = paramParcel1.readString();
          localzzeo = zzeo.zza.zzG(paramParcel1.readStrongBinder());
          if (paramParcel1.readInt() == 0) {
            break label872;
          }
        }
        label872:
        for (NativeAdOptionsParcel localNativeAdOptionsParcel = NativeAdOptionsParcel.CREATOR.zze(paramParcel1);; localNativeAdOptionsParcel = null)
        {
          zza(localzzd1, localAdRequestParcel1, str1, str2, localzzeo, localNativeAdOptionsParcel, paramParcel1.createStringArrayList());
          paramParcel2.writeNoException();
          break;
          localAdRequestParcel1 = null;
          break label802;
        }
        paramParcel1.enforceInterface("com.google.android.gms.ads.internal.mediation.client.IMediationAdapter");
        zzeq localzzeq = zzdV();
        paramParcel2.writeNoException();
        if (localzzeq != null) {
          localObject = localzzeq.asBinder();
        }
        paramParcel2.writeStrongBinder((IBinder)localObject);
        continue;
        paramParcel1.enforceInterface("com.google.android.gms.ads.internal.mediation.client.IMediationAdapter");
        zzer localzzer = zzdW();
        paramParcel2.writeNoException();
        if (localzzer != null) {
          localObject = localzzer.asBinder();
        }
        paramParcel2.writeStrongBinder((IBinder)localObject);
        continue;
        paramParcel1.enforceInterface("com.google.android.gms.ads.internal.mediation.client.IMediationAdapter");
        Bundle localBundle3 = zzdX();
        paramParcel2.writeNoException();
        if (localBundle3 != null)
        {
          paramParcel2.writeInt(i);
          localBundle3.writeToParcel(paramParcel2, i);
        }
        else
        {
          paramParcel2.writeInt(0);
          continue;
          paramParcel1.enforceInterface("com.google.android.gms.ads.internal.mediation.client.IMediationAdapter");
          Bundle localBundle2 = zzdY();
          paramParcel2.writeNoException();
          if (localBundle2 != null)
          {
            paramParcel2.writeInt(i);
            localBundle2.writeToParcel(paramParcel2, i);
          }
          else
          {
            paramParcel2.writeInt(0);
            continue;
            paramParcel1.enforceInterface("com.google.android.gms.ads.internal.mediation.client.IMediationAdapter");
            Bundle localBundle1 = zzdZ();
            paramParcel2.writeNoException();
            if (localBundle1 != null)
            {
              paramParcel2.writeInt(i);
              localBundle1.writeToParcel(paramParcel2, i);
            }
            else
            {
              paramParcel2.writeInt(0);
            }
          }
        }
      }
    }
    
    private static class zza
      implements zzen
    {
      private IBinder zznJ;
      
      zza(IBinder paramIBinder)
      {
        this.zznJ = paramIBinder;
      }
      
      public IBinder asBinder()
      {
        return this.zznJ;
      }
      
      public void destroy()
        throws RemoteException
      {
        Parcel localParcel1 = Parcel.obtain();
        Parcel localParcel2 = Parcel.obtain();
        try
        {
          localParcel1.writeInterfaceToken("com.google.android.gms.ads.internal.mediation.client.IMediationAdapter");
          this.zznJ.transact(5, localParcel1, localParcel2, 0);
          localParcel2.readException();
          return;
        }
        finally
        {
          localParcel2.recycle();
          localParcel1.recycle();
        }
      }
      
      public zzd getView()
        throws RemoteException
      {
        Parcel localParcel1 = Parcel.obtain();
        Parcel localParcel2 = Parcel.obtain();
        try
        {
          localParcel1.writeInterfaceToken("com.google.android.gms.ads.internal.mediation.client.IMediationAdapter");
          this.zznJ.transact(2, localParcel1, localParcel2, 0);
          localParcel2.readException();
          zzd localzzd = zzd.zza.zzbk(localParcel2.readStrongBinder());
          return localzzd;
        }
        finally
        {
          localParcel2.recycle();
          localParcel1.recycle();
        }
      }
      
      public boolean isInitialized()
        throws RemoteException
      {
        boolean bool = false;
        Parcel localParcel1 = Parcel.obtain();
        Parcel localParcel2 = Parcel.obtain();
        try
        {
          localParcel1.writeInterfaceToken("com.google.android.gms.ads.internal.mediation.client.IMediationAdapter");
          this.zznJ.transact(13, localParcel1, localParcel2, 0);
          localParcel2.readException();
          int i = localParcel2.readInt();
          if (i != 0) {
            bool = true;
          }
          return bool;
        }
        finally
        {
          localParcel2.recycle();
          localParcel1.recycle();
        }
      }
      
      public void pause()
        throws RemoteException
      {
        Parcel localParcel1 = Parcel.obtain();
        Parcel localParcel2 = Parcel.obtain();
        try
        {
          localParcel1.writeInterfaceToken("com.google.android.gms.ads.internal.mediation.client.IMediationAdapter");
          this.zznJ.transact(8, localParcel1, localParcel2, 0);
          localParcel2.readException();
          return;
        }
        finally
        {
          localParcel2.recycle();
          localParcel1.recycle();
        }
      }
      
      public void resume()
        throws RemoteException
      {
        Parcel localParcel1 = Parcel.obtain();
        Parcel localParcel2 = Parcel.obtain();
        try
        {
          localParcel1.writeInterfaceToken("com.google.android.gms.ads.internal.mediation.client.IMediationAdapter");
          this.zznJ.transact(9, localParcel1, localParcel2, 0);
          localParcel2.readException();
          return;
        }
        finally
        {
          localParcel2.recycle();
          localParcel1.recycle();
        }
      }
      
      public void showInterstitial()
        throws RemoteException
      {
        Parcel localParcel1 = Parcel.obtain();
        Parcel localParcel2 = Parcel.obtain();
        try
        {
          localParcel1.writeInterfaceToken("com.google.android.gms.ads.internal.mediation.client.IMediationAdapter");
          this.zznJ.transact(4, localParcel1, localParcel2, 0);
          localParcel2.readException();
          return;
        }
        finally
        {
          localParcel2.recycle();
          localParcel1.recycle();
        }
      }
      
      public void showVideo()
        throws RemoteException
      {
        Parcel localParcel1 = Parcel.obtain();
        Parcel localParcel2 = Parcel.obtain();
        try
        {
          localParcel1.writeInterfaceToken("com.google.android.gms.ads.internal.mediation.client.IMediationAdapter");
          this.zznJ.transact(12, localParcel1, localParcel2, 0);
          localParcel2.readException();
          return;
        }
        finally
        {
          localParcel2.recycle();
          localParcel1.recycle();
        }
      }
      
      /* Error */
      public void zza(AdRequestParcel paramAdRequestParcel, String paramString)
        throws RemoteException
      {
        // Byte code:
        //   0: invokestatic 29	android/os/Parcel:obtain	()Landroid/os/Parcel;
        //   3: astore_3
        //   4: invokestatic 29	android/os/Parcel:obtain	()Landroid/os/Parcel;
        //   7: astore 4
        //   9: aload_3
        //   10: ldc 31
        //   12: invokevirtual 35	android/os/Parcel:writeInterfaceToken	(Ljava/lang/String;)V
        //   15: aload_1
        //   16: ifnull +50 -> 66
        //   19: aload_3
        //   20: iconst_1
        //   21: invokevirtual 73	android/os/Parcel:writeInt	(I)V
        //   24: aload_1
        //   25: aload_3
        //   26: iconst_0
        //   27: invokevirtual 79	com/google/android/gms/ads/internal/client/AdRequestParcel:writeToParcel	(Landroid/os/Parcel;I)V
        //   30: aload_3
        //   31: aload_2
        //   32: invokevirtual 82	android/os/Parcel:writeString	(Ljava/lang/String;)V
        //   35: aload_0
        //   36: getfield 18	com/google/android/gms/internal/zzen$zza$zza:zznJ	Landroid/os/IBinder;
        //   39: bipush 11
        //   41: aload_3
        //   42: aload 4
        //   44: iconst_0
        //   45: invokeinterface 41 5 0
        //   50: pop
        //   51: aload 4
        //   53: invokevirtual 44	android/os/Parcel:readException	()V
        //   56: aload 4
        //   58: invokevirtual 47	android/os/Parcel:recycle	()V
        //   61: aload_3
        //   62: invokevirtual 47	android/os/Parcel:recycle	()V
        //   65: return
        //   66: aload_3
        //   67: iconst_0
        //   68: invokevirtual 73	android/os/Parcel:writeInt	(I)V
        //   71: goto -41 -> 30
        //   74: astore 5
        //   76: aload 4
        //   78: invokevirtual 47	android/os/Parcel:recycle	()V
        //   81: aload_3
        //   82: invokevirtual 47	android/os/Parcel:recycle	()V
        //   85: aload 5
        //   87: athrow
        // Local variable table:
        //   start	length	slot	name	signature
        //   0	88	0	this	zza
        //   0	88	1	paramAdRequestParcel	AdRequestParcel
        //   0	88	2	paramString	String
        //   3	79	3	localParcel1	Parcel
        //   7	70	4	localParcel2	Parcel
        //   74	12	5	localObject	Object
        // Exception table:
        //   from	to	target	type
        //   9	56	74	finally
        //   66	71	74	finally
      }
      
      /* Error */
      public void zza(zzd paramzzd, AdRequestParcel paramAdRequestParcel, String paramString1, zza paramzza, String paramString2)
        throws RemoteException
      {
        // Byte code:
        //   0: aconst_null
        //   1: astore 6
        //   3: invokestatic 29	android/os/Parcel:obtain	()Landroid/os/Parcel;
        //   6: astore 7
        //   8: invokestatic 29	android/os/Parcel:obtain	()Landroid/os/Parcel;
        //   11: astore 8
        //   13: aload 7
        //   15: ldc 31
        //   17: invokevirtual 35	android/os/Parcel:writeInterfaceToken	(Ljava/lang/String;)V
        //   20: aload_1
        //   21: ifnull +102 -> 123
        //   24: aload_1
        //   25: invokeinterface 87 1 0
        //   30: astore 10
        //   32: aload 7
        //   34: aload 10
        //   36: invokevirtual 90	android/os/Parcel:writeStrongBinder	(Landroid/os/IBinder;)V
        //   39: aload_2
        //   40: ifnull +89 -> 129
        //   43: aload 7
        //   45: iconst_1
        //   46: invokevirtual 73	android/os/Parcel:writeInt	(I)V
        //   49: aload_2
        //   50: aload 7
        //   52: iconst_0
        //   53: invokevirtual 79	com/google/android/gms/ads/internal/client/AdRequestParcel:writeToParcel	(Landroid/os/Parcel;I)V
        //   56: aload 7
        //   58: aload_3
        //   59: invokevirtual 82	android/os/Parcel:writeString	(Ljava/lang/String;)V
        //   62: aload 4
        //   64: ifnull +12 -> 76
        //   67: aload 4
        //   69: invokeinterface 93 1 0
        //   74: astore 6
        //   76: aload 7
        //   78: aload 6
        //   80: invokevirtual 90	android/os/Parcel:writeStrongBinder	(Landroid/os/IBinder;)V
        //   83: aload 7
        //   85: aload 5
        //   87: invokevirtual 82	android/os/Parcel:writeString	(Ljava/lang/String;)V
        //   90: aload_0
        //   91: getfield 18	com/google/android/gms/internal/zzen$zza$zza:zznJ	Landroid/os/IBinder;
        //   94: bipush 10
        //   96: aload 7
        //   98: aload 8
        //   100: iconst_0
        //   101: invokeinterface 41 5 0
        //   106: pop
        //   107: aload 8
        //   109: invokevirtual 44	android/os/Parcel:readException	()V
        //   112: aload 8
        //   114: invokevirtual 47	android/os/Parcel:recycle	()V
        //   117: aload 7
        //   119: invokevirtual 47	android/os/Parcel:recycle	()V
        //   122: return
        //   123: aconst_null
        //   124: astore 10
        //   126: goto -94 -> 32
        //   129: aload 7
        //   131: iconst_0
        //   132: invokevirtual 73	android/os/Parcel:writeInt	(I)V
        //   135: goto -79 -> 56
        //   138: astore 9
        //   140: aload 8
        //   142: invokevirtual 47	android/os/Parcel:recycle	()V
        //   145: aload 7
        //   147: invokevirtual 47	android/os/Parcel:recycle	()V
        //   150: aload 9
        //   152: athrow
        // Local variable table:
        //   start	length	slot	name	signature
        //   0	153	0	this	zza
        //   0	153	1	paramzzd	zzd
        //   0	153	2	paramAdRequestParcel	AdRequestParcel
        //   0	153	3	paramString1	String
        //   0	153	4	paramzza	zza
        //   0	153	5	paramString2	String
        //   1	78	6	localIBinder1	IBinder
        //   6	140	7	localParcel1	Parcel
        //   11	130	8	localParcel2	Parcel
        //   138	13	9	localObject	Object
        //   30	95	10	localIBinder2	IBinder
        // Exception table:
        //   from	to	target	type
        //   13	112	138	finally
        //   129	135	138	finally
      }
      
      /* Error */
      public void zza(zzd paramzzd, AdRequestParcel paramAdRequestParcel, String paramString, zzeo paramzzeo)
        throws RemoteException
      {
        // Byte code:
        //   0: aconst_null
        //   1: astore 5
        //   3: invokestatic 29	android/os/Parcel:obtain	()Landroid/os/Parcel;
        //   6: astore 6
        //   8: invokestatic 29	android/os/Parcel:obtain	()Landroid/os/Parcel;
        //   11: astore 7
        //   13: aload 6
        //   15: ldc 31
        //   17: invokevirtual 35	android/os/Parcel:writeInterfaceToken	(Ljava/lang/String;)V
        //   20: aload_1
        //   21: ifnull +94 -> 115
        //   24: aload_1
        //   25: invokeinterface 87 1 0
        //   30: astore 9
        //   32: aload 6
        //   34: aload 9
        //   36: invokevirtual 90	android/os/Parcel:writeStrongBinder	(Landroid/os/IBinder;)V
        //   39: aload_2
        //   40: ifnull +81 -> 121
        //   43: aload 6
        //   45: iconst_1
        //   46: invokevirtual 73	android/os/Parcel:writeInt	(I)V
        //   49: aload_2
        //   50: aload 6
        //   52: iconst_0
        //   53: invokevirtual 79	com/google/android/gms/ads/internal/client/AdRequestParcel:writeToParcel	(Landroid/os/Parcel;I)V
        //   56: aload 6
        //   58: aload_3
        //   59: invokevirtual 82	android/os/Parcel:writeString	(Ljava/lang/String;)V
        //   62: aload 4
        //   64: ifnull +12 -> 76
        //   67: aload 4
        //   69: invokeinterface 97 1 0
        //   74: astore 5
        //   76: aload 6
        //   78: aload 5
        //   80: invokevirtual 90	android/os/Parcel:writeStrongBinder	(Landroid/os/IBinder;)V
        //   83: aload_0
        //   84: getfield 18	com/google/android/gms/internal/zzen$zza$zza:zznJ	Landroid/os/IBinder;
        //   87: iconst_3
        //   88: aload 6
        //   90: aload 7
        //   92: iconst_0
        //   93: invokeinterface 41 5 0
        //   98: pop
        //   99: aload 7
        //   101: invokevirtual 44	android/os/Parcel:readException	()V
        //   104: aload 7
        //   106: invokevirtual 47	android/os/Parcel:recycle	()V
        //   109: aload 6
        //   111: invokevirtual 47	android/os/Parcel:recycle	()V
        //   114: return
        //   115: aconst_null
        //   116: astore 9
        //   118: goto -86 -> 32
        //   121: aload 6
        //   123: iconst_0
        //   124: invokevirtual 73	android/os/Parcel:writeInt	(I)V
        //   127: goto -71 -> 56
        //   130: astore 8
        //   132: aload 7
        //   134: invokevirtual 47	android/os/Parcel:recycle	()V
        //   137: aload 6
        //   139: invokevirtual 47	android/os/Parcel:recycle	()V
        //   142: aload 8
        //   144: athrow
        // Local variable table:
        //   start	length	slot	name	signature
        //   0	145	0	this	zza
        //   0	145	1	paramzzd	zzd
        //   0	145	2	paramAdRequestParcel	AdRequestParcel
        //   0	145	3	paramString	String
        //   0	145	4	paramzzeo	zzeo
        //   1	78	5	localIBinder1	IBinder
        //   6	132	6	localParcel1	Parcel
        //   11	122	7	localParcel2	Parcel
        //   130	13	8	localObject	Object
        //   30	87	9	localIBinder2	IBinder
        // Exception table:
        //   from	to	target	type
        //   13	104	130	finally
        //   121	127	130	finally
      }
      
      /* Error */
      public void zza(zzd paramzzd, AdRequestParcel paramAdRequestParcel, String paramString1, String paramString2, zzeo paramzzeo)
        throws RemoteException
      {
        // Byte code:
        //   0: aconst_null
        //   1: astore 6
        //   3: invokestatic 29	android/os/Parcel:obtain	()Landroid/os/Parcel;
        //   6: astore 7
        //   8: invokestatic 29	android/os/Parcel:obtain	()Landroid/os/Parcel;
        //   11: astore 8
        //   13: aload 7
        //   15: ldc 31
        //   17: invokevirtual 35	android/os/Parcel:writeInterfaceToken	(Ljava/lang/String;)V
        //   20: aload_1
        //   21: ifnull +102 -> 123
        //   24: aload_1
        //   25: invokeinterface 87 1 0
        //   30: astore 10
        //   32: aload 7
        //   34: aload 10
        //   36: invokevirtual 90	android/os/Parcel:writeStrongBinder	(Landroid/os/IBinder;)V
        //   39: aload_2
        //   40: ifnull +89 -> 129
        //   43: aload 7
        //   45: iconst_1
        //   46: invokevirtual 73	android/os/Parcel:writeInt	(I)V
        //   49: aload_2
        //   50: aload 7
        //   52: iconst_0
        //   53: invokevirtual 79	com/google/android/gms/ads/internal/client/AdRequestParcel:writeToParcel	(Landroid/os/Parcel;I)V
        //   56: aload 7
        //   58: aload_3
        //   59: invokevirtual 82	android/os/Parcel:writeString	(Ljava/lang/String;)V
        //   62: aload 7
        //   64: aload 4
        //   66: invokevirtual 82	android/os/Parcel:writeString	(Ljava/lang/String;)V
        //   69: aload 5
        //   71: ifnull +12 -> 83
        //   74: aload 5
        //   76: invokeinterface 97 1 0
        //   81: astore 6
        //   83: aload 7
        //   85: aload 6
        //   87: invokevirtual 90	android/os/Parcel:writeStrongBinder	(Landroid/os/IBinder;)V
        //   90: aload_0
        //   91: getfield 18	com/google/android/gms/internal/zzen$zza$zza:zznJ	Landroid/os/IBinder;
        //   94: bipush 7
        //   96: aload 7
        //   98: aload 8
        //   100: iconst_0
        //   101: invokeinterface 41 5 0
        //   106: pop
        //   107: aload 8
        //   109: invokevirtual 44	android/os/Parcel:readException	()V
        //   112: aload 8
        //   114: invokevirtual 47	android/os/Parcel:recycle	()V
        //   117: aload 7
        //   119: invokevirtual 47	android/os/Parcel:recycle	()V
        //   122: return
        //   123: aconst_null
        //   124: astore 10
        //   126: goto -94 -> 32
        //   129: aload 7
        //   131: iconst_0
        //   132: invokevirtual 73	android/os/Parcel:writeInt	(I)V
        //   135: goto -79 -> 56
        //   138: astore 9
        //   140: aload 8
        //   142: invokevirtual 47	android/os/Parcel:recycle	()V
        //   145: aload 7
        //   147: invokevirtual 47	android/os/Parcel:recycle	()V
        //   150: aload 9
        //   152: athrow
        // Local variable table:
        //   start	length	slot	name	signature
        //   0	153	0	this	zza
        //   0	153	1	paramzzd	zzd
        //   0	153	2	paramAdRequestParcel	AdRequestParcel
        //   0	153	3	paramString1	String
        //   0	153	4	paramString2	String
        //   0	153	5	paramzzeo	zzeo
        //   1	85	6	localIBinder1	IBinder
        //   6	140	7	localParcel1	Parcel
        //   11	130	8	localParcel2	Parcel
        //   138	13	9	localObject	Object
        //   30	95	10	localIBinder2	IBinder
        // Exception table:
        //   from	to	target	type
        //   13	112	138	finally
        //   129	135	138	finally
      }
      
      public void zza(zzd paramzzd, AdRequestParcel paramAdRequestParcel, String paramString1, String paramString2, zzeo paramzzeo, NativeAdOptionsParcel paramNativeAdOptionsParcel, List<String> paramList)
        throws RemoteException
      {
        IBinder localIBinder1 = null;
        Parcel localParcel1 = Parcel.obtain();
        Parcel localParcel2 = Parcel.obtain();
        label179:
        for (;;)
        {
          try
          {
            localParcel1.writeInterfaceToken("com.google.android.gms.ads.internal.mediation.client.IMediationAdapter");
            IBinder localIBinder2;
            if (paramzzd != null)
            {
              localIBinder2 = paramzzd.asBinder();
              localParcel1.writeStrongBinder(localIBinder2);
              if (paramAdRequestParcel != null)
              {
                localParcel1.writeInt(1);
                paramAdRequestParcel.writeToParcel(localParcel1, 0);
                localParcel1.writeString(paramString1);
                localParcel1.writeString(paramString2);
                if (paramzzeo != null) {
                  localIBinder1 = paramzzeo.asBinder();
                }
                localParcel1.writeStrongBinder(localIBinder1);
                if (paramNativeAdOptionsParcel == null) {
                  break label179;
                }
                localParcel1.writeInt(1);
                paramNativeAdOptionsParcel.writeToParcel(localParcel1, 0);
                localParcel1.writeStringList(paramList);
                this.zznJ.transact(14, localParcel1, localParcel2, 0);
                localParcel2.readException();
              }
            }
            else
            {
              localIBinder2 = null;
              continue;
            }
            localParcel1.writeInt(0);
            continue;
            localParcel1.writeInt(0);
          }
          finally
          {
            localParcel2.recycle();
            localParcel1.recycle();
          }
        }
      }
      
      public void zza(zzd paramzzd, AdSizeParcel paramAdSizeParcel, AdRequestParcel paramAdRequestParcel, String paramString, zzeo paramzzeo)
        throws RemoteException
      {
        IBinder localIBinder1 = null;
        Parcel localParcel1 = Parcel.obtain();
        Parcel localParcel2 = Parcel.obtain();
        label163:
        for (;;)
        {
          try
          {
            localParcel1.writeInterfaceToken("com.google.android.gms.ads.internal.mediation.client.IMediationAdapter");
            IBinder localIBinder2;
            if (paramzzd != null)
            {
              localIBinder2 = paramzzd.asBinder();
              localParcel1.writeStrongBinder(localIBinder2);
              if (paramAdSizeParcel != null)
              {
                localParcel1.writeInt(1);
                paramAdSizeParcel.writeToParcel(localParcel1, 0);
                if (paramAdRequestParcel == null) {
                  break label163;
                }
                localParcel1.writeInt(1);
                paramAdRequestParcel.writeToParcel(localParcel1, 0);
                localParcel1.writeString(paramString);
                if (paramzzeo != null) {
                  localIBinder1 = paramzzeo.asBinder();
                }
                localParcel1.writeStrongBinder(localIBinder1);
                this.zznJ.transact(1, localParcel1, localParcel2, 0);
                localParcel2.readException();
              }
            }
            else
            {
              localIBinder2 = null;
              continue;
            }
            localParcel1.writeInt(0);
            continue;
            localParcel1.writeInt(0);
          }
          finally
          {
            localParcel2.recycle();
            localParcel1.recycle();
          }
        }
      }
      
      public void zza(zzd paramzzd, AdSizeParcel paramAdSizeParcel, AdRequestParcel paramAdRequestParcel, String paramString1, String paramString2, zzeo paramzzeo)
        throws RemoteException
      {
        IBinder localIBinder1 = null;
        Parcel localParcel1 = Parcel.obtain();
        Parcel localParcel2 = Parcel.obtain();
        label171:
        for (;;)
        {
          try
          {
            localParcel1.writeInterfaceToken("com.google.android.gms.ads.internal.mediation.client.IMediationAdapter");
            IBinder localIBinder2;
            if (paramzzd != null)
            {
              localIBinder2 = paramzzd.asBinder();
              localParcel1.writeStrongBinder(localIBinder2);
              if (paramAdSizeParcel != null)
              {
                localParcel1.writeInt(1);
                paramAdSizeParcel.writeToParcel(localParcel1, 0);
                if (paramAdRequestParcel == null) {
                  break label171;
                }
                localParcel1.writeInt(1);
                paramAdRequestParcel.writeToParcel(localParcel1, 0);
                localParcel1.writeString(paramString1);
                localParcel1.writeString(paramString2);
                if (paramzzeo != null) {
                  localIBinder1 = paramzzeo.asBinder();
                }
                localParcel1.writeStrongBinder(localIBinder1);
                this.zznJ.transact(6, localParcel1, localParcel2, 0);
                localParcel2.readException();
              }
            }
            else
            {
              localIBinder2 = null;
              continue;
            }
            localParcel1.writeInt(0);
            continue;
            localParcel1.writeInt(0);
          }
          finally
          {
            localParcel2.recycle();
            localParcel1.recycle();
          }
        }
      }
      
      public zzeq zzdV()
        throws RemoteException
      {
        Parcel localParcel1 = Parcel.obtain();
        Parcel localParcel2 = Parcel.obtain();
        try
        {
          localParcel1.writeInterfaceToken("com.google.android.gms.ads.internal.mediation.client.IMediationAdapter");
          this.zznJ.transact(15, localParcel1, localParcel2, 0);
          localParcel2.readException();
          zzeq localzzeq = zzeq.zza.zzI(localParcel2.readStrongBinder());
          return localzzeq;
        }
        finally
        {
          localParcel2.recycle();
          localParcel1.recycle();
        }
      }
      
      public zzer zzdW()
        throws RemoteException
      {
        Parcel localParcel1 = Parcel.obtain();
        Parcel localParcel2 = Parcel.obtain();
        try
        {
          localParcel1.writeInterfaceToken("com.google.android.gms.ads.internal.mediation.client.IMediationAdapter");
          this.zznJ.transact(16, localParcel1, localParcel2, 0);
          localParcel2.readException();
          zzer localzzer = zzer.zza.zzJ(localParcel2.readStrongBinder());
          return localzzer;
        }
        finally
        {
          localParcel2.recycle();
          localParcel1.recycle();
        }
      }
      
      /* Error */
      public Bundle zzdX()
        throws RemoteException
      {
        // Byte code:
        //   0: invokestatic 29	android/os/Parcel:obtain	()Landroid/os/Parcel;
        //   3: astore_1
        //   4: invokestatic 29	android/os/Parcel:obtain	()Landroid/os/Parcel;
        //   7: astore_2
        //   8: aload_1
        //   9: ldc 31
        //   11: invokevirtual 35	android/os/Parcel:writeInterfaceToken	(Ljava/lang/String;)V
        //   14: aload_0
        //   15: getfield 18	com/google/android/gms/internal/zzen$zza$zza:zznJ	Landroid/os/IBinder;
        //   18: bipush 17
        //   20: aload_1
        //   21: aload_2
        //   22: iconst_0
        //   23: invokeinterface 41 5 0
        //   28: pop
        //   29: aload_2
        //   30: invokevirtual 44	android/os/Parcel:readException	()V
        //   33: aload_2
        //   34: invokevirtual 64	android/os/Parcel:readInt	()I
        //   37: ifeq +28 -> 65
        //   40: getstatic 135	android/os/Bundle:CREATOR	Landroid/os/Parcelable$Creator;
        //   43: aload_2
        //   44: invokeinterface 141 2 0
        //   49: checkcast 131	android/os/Bundle
        //   52: astore 5
        //   54: aload_2
        //   55: invokevirtual 47	android/os/Parcel:recycle	()V
        //   58: aload_1
        //   59: invokevirtual 47	android/os/Parcel:recycle	()V
        //   62: aload 5
        //   64: areturn
        //   65: aconst_null
        //   66: astore 5
        //   68: goto -14 -> 54
        //   71: astore_3
        //   72: aload_2
        //   73: invokevirtual 47	android/os/Parcel:recycle	()V
        //   76: aload_1
        //   77: invokevirtual 47	android/os/Parcel:recycle	()V
        //   80: aload_3
        //   81: athrow
        // Local variable table:
        //   start	length	slot	name	signature
        //   0	82	0	this	zza
        //   3	74	1	localParcel1	Parcel
        //   7	66	2	localParcel2	Parcel
        //   71	10	3	localObject	Object
        //   52	15	5	localBundle	Bundle
        // Exception table:
        //   from	to	target	type
        //   8	54	71	finally
      }
      
      /* Error */
      public Bundle zzdY()
        throws RemoteException
      {
        // Byte code:
        //   0: invokestatic 29	android/os/Parcel:obtain	()Landroid/os/Parcel;
        //   3: astore_1
        //   4: invokestatic 29	android/os/Parcel:obtain	()Landroid/os/Parcel;
        //   7: astore_2
        //   8: aload_1
        //   9: ldc 31
        //   11: invokevirtual 35	android/os/Parcel:writeInterfaceToken	(Ljava/lang/String;)V
        //   14: aload_0
        //   15: getfield 18	com/google/android/gms/internal/zzen$zza$zza:zznJ	Landroid/os/IBinder;
        //   18: bipush 18
        //   20: aload_1
        //   21: aload_2
        //   22: iconst_0
        //   23: invokeinterface 41 5 0
        //   28: pop
        //   29: aload_2
        //   30: invokevirtual 44	android/os/Parcel:readException	()V
        //   33: aload_2
        //   34: invokevirtual 64	android/os/Parcel:readInt	()I
        //   37: ifeq +28 -> 65
        //   40: getstatic 135	android/os/Bundle:CREATOR	Landroid/os/Parcelable$Creator;
        //   43: aload_2
        //   44: invokeinterface 141 2 0
        //   49: checkcast 131	android/os/Bundle
        //   52: astore 5
        //   54: aload_2
        //   55: invokevirtual 47	android/os/Parcel:recycle	()V
        //   58: aload_1
        //   59: invokevirtual 47	android/os/Parcel:recycle	()V
        //   62: aload 5
        //   64: areturn
        //   65: aconst_null
        //   66: astore 5
        //   68: goto -14 -> 54
        //   71: astore_3
        //   72: aload_2
        //   73: invokevirtual 47	android/os/Parcel:recycle	()V
        //   76: aload_1
        //   77: invokevirtual 47	android/os/Parcel:recycle	()V
        //   80: aload_3
        //   81: athrow
        // Local variable table:
        //   start	length	slot	name	signature
        //   0	82	0	this	zza
        //   3	74	1	localParcel1	Parcel
        //   7	66	2	localParcel2	Parcel
        //   71	10	3	localObject	Object
        //   52	15	5	localBundle	Bundle
        // Exception table:
        //   from	to	target	type
        //   8	54	71	finally
      }
      
      /* Error */
      public Bundle zzdZ()
        throws RemoteException
      {
        // Byte code:
        //   0: invokestatic 29	android/os/Parcel:obtain	()Landroid/os/Parcel;
        //   3: astore_1
        //   4: invokestatic 29	android/os/Parcel:obtain	()Landroid/os/Parcel;
        //   7: astore_2
        //   8: aload_1
        //   9: ldc 31
        //   11: invokevirtual 35	android/os/Parcel:writeInterfaceToken	(Ljava/lang/String;)V
        //   14: aload_0
        //   15: getfield 18	com/google/android/gms/internal/zzen$zza$zza:zznJ	Landroid/os/IBinder;
        //   18: bipush 19
        //   20: aload_1
        //   21: aload_2
        //   22: iconst_0
        //   23: invokeinterface 41 5 0
        //   28: pop
        //   29: aload_2
        //   30: invokevirtual 44	android/os/Parcel:readException	()V
        //   33: aload_2
        //   34: invokevirtual 64	android/os/Parcel:readInt	()I
        //   37: ifeq +28 -> 65
        //   40: getstatic 135	android/os/Bundle:CREATOR	Landroid/os/Parcelable$Creator;
        //   43: aload_2
        //   44: invokeinterface 141 2 0
        //   49: checkcast 131	android/os/Bundle
        //   52: astore 5
        //   54: aload_2
        //   55: invokevirtual 47	android/os/Parcel:recycle	()V
        //   58: aload_1
        //   59: invokevirtual 47	android/os/Parcel:recycle	()V
        //   62: aload 5
        //   64: areturn
        //   65: aconst_null
        //   66: astore 5
        //   68: goto -14 -> 54
        //   71: astore_3
        //   72: aload_2
        //   73: invokevirtual 47	android/os/Parcel:recycle	()V
        //   76: aload_1
        //   77: invokevirtual 47	android/os/Parcel:recycle	()V
        //   80: aload_3
        //   81: athrow
        // Local variable table:
        //   start	length	slot	name	signature
        //   0	82	0	this	zza
        //   3	74	1	localParcel1	Parcel
        //   7	66	2	localParcel2	Parcel
        //   71	10	3	localObject	Object
        //   52	15	5	localBundle	Bundle
        // Exception table:
        //   from	to	target	type
        //   8	54	71	finally
      }
    }
  }
}


/* Location:              /Users/tjledwith/Downloads/dex2jar-0.0.9.8/classes_dex2jar.jar!/com/google/android/gms/internal/zzen.class
 * Java compiler version: 6 (50.0)
 * JD-Core Version:       0.7.1
 */