package com.google.android.gms.internal;

import android.os.Binder;
import android.os.IBinder;
import android.os.IInterface;
import android.os.Parcel;
import android.os.RemoteException;

public abstract interface zzeo
  extends IInterface
{
  public abstract void onAdClicked()
    throws RemoteException;
  
  public abstract void onAdClosed()
    throws RemoteException;
  
  public abstract void onAdFailedToLoad(int paramInt)
    throws RemoteException;
  
  public abstract void onAdLeftApplication()
    throws RemoteException;
  
  public abstract void onAdLoaded()
    throws RemoteException;
  
  public abstract void onAdOpened()
    throws RemoteException;
  
  public abstract void zza(zzep paramzzep)
    throws RemoteException;
  
  public static abstract class zza
    extends Binder
    implements zzeo
  {
    public zza()
    {
      attachInterface(this, "com.google.android.gms.ads.internal.mediation.client.IMediationAdapterListener");
    }
    
    public static zzeo zzG(IBinder paramIBinder)
    {
      Object localObject;
      if (paramIBinder == null) {
        localObject = null;
      }
      for (;;)
      {
        return (zzeo)localObject;
        IInterface localIInterface = paramIBinder.queryLocalInterface("com.google.android.gms.ads.internal.mediation.client.IMediationAdapterListener");
        if ((localIInterface != null) && ((localIInterface instanceof zzeo))) {
          localObject = (zzeo)localIInterface;
        } else {
          localObject = new zza(paramIBinder);
        }
      }
    }
    
    public IBinder asBinder()
    {
      return this;
    }
    
    public boolean onTransact(int paramInt1, Parcel paramParcel1, Parcel paramParcel2, int paramInt2)
      throws RemoteException
    {
      boolean bool = true;
      switch (paramInt1)
      {
      default: 
        bool = super.onTransact(paramInt1, paramParcel1, paramParcel2, paramInt2);
      }
      for (;;)
      {
        return bool;
        paramParcel2.writeString("com.google.android.gms.ads.internal.mediation.client.IMediationAdapterListener");
        continue;
        paramParcel1.enforceInterface("com.google.android.gms.ads.internal.mediation.client.IMediationAdapterListener");
        onAdClicked();
        paramParcel2.writeNoException();
        continue;
        paramParcel1.enforceInterface("com.google.android.gms.ads.internal.mediation.client.IMediationAdapterListener");
        onAdClosed();
        paramParcel2.writeNoException();
        continue;
        paramParcel1.enforceInterface("com.google.android.gms.ads.internal.mediation.client.IMediationAdapterListener");
        onAdFailedToLoad(paramParcel1.readInt());
        paramParcel2.writeNoException();
        continue;
        paramParcel1.enforceInterface("com.google.android.gms.ads.internal.mediation.client.IMediationAdapterListener");
        onAdLeftApplication();
        paramParcel2.writeNoException();
        continue;
        paramParcel1.enforceInterface("com.google.android.gms.ads.internal.mediation.client.IMediationAdapterListener");
        onAdOpened();
        paramParcel2.writeNoException();
        continue;
        paramParcel1.enforceInterface("com.google.android.gms.ads.internal.mediation.client.IMediationAdapterListener");
        onAdLoaded();
        paramParcel2.writeNoException();
        continue;
        paramParcel1.enforceInterface("com.google.android.gms.ads.internal.mediation.client.IMediationAdapterListener");
        zza(zzep.zza.zzH(paramParcel1.readStrongBinder()));
        paramParcel2.writeNoException();
      }
    }
    
    private static class zza
      implements zzeo
    {
      private IBinder zznJ;
      
      zza(IBinder paramIBinder)
      {
        this.zznJ = paramIBinder;
      }
      
      public IBinder asBinder()
      {
        return this.zznJ;
      }
      
      public void onAdClicked()
        throws RemoteException
      {
        Parcel localParcel1 = Parcel.obtain();
        Parcel localParcel2 = Parcel.obtain();
        try
        {
          localParcel1.writeInterfaceToken("com.google.android.gms.ads.internal.mediation.client.IMediationAdapterListener");
          this.zznJ.transact(1, localParcel1, localParcel2, 0);
          localParcel2.readException();
          return;
        }
        finally
        {
          localParcel2.recycle();
          localParcel1.recycle();
        }
      }
      
      public void onAdClosed()
        throws RemoteException
      {
        Parcel localParcel1 = Parcel.obtain();
        Parcel localParcel2 = Parcel.obtain();
        try
        {
          localParcel1.writeInterfaceToken("com.google.android.gms.ads.internal.mediation.client.IMediationAdapterListener");
          this.zznJ.transact(2, localParcel1, localParcel2, 0);
          localParcel2.readException();
          return;
        }
        finally
        {
          localParcel2.recycle();
          localParcel1.recycle();
        }
      }
      
      public void onAdFailedToLoad(int paramInt)
        throws RemoteException
      {
        Parcel localParcel1 = Parcel.obtain();
        Parcel localParcel2 = Parcel.obtain();
        try
        {
          localParcel1.writeInterfaceToken("com.google.android.gms.ads.internal.mediation.client.IMediationAdapterListener");
          localParcel1.writeInt(paramInt);
          this.zznJ.transact(3, localParcel1, localParcel2, 0);
          localParcel2.readException();
          return;
        }
        finally
        {
          localParcel2.recycle();
          localParcel1.recycle();
        }
      }
      
      public void onAdLeftApplication()
        throws RemoteException
      {
        Parcel localParcel1 = Parcel.obtain();
        Parcel localParcel2 = Parcel.obtain();
        try
        {
          localParcel1.writeInterfaceToken("com.google.android.gms.ads.internal.mediation.client.IMediationAdapterListener");
          this.zznJ.transact(4, localParcel1, localParcel2, 0);
          localParcel2.readException();
          return;
        }
        finally
        {
          localParcel2.recycle();
          localParcel1.recycle();
        }
      }
      
      public void onAdLoaded()
        throws RemoteException
      {
        Parcel localParcel1 = Parcel.obtain();
        Parcel localParcel2 = Parcel.obtain();
        try
        {
          localParcel1.writeInterfaceToken("com.google.android.gms.ads.internal.mediation.client.IMediationAdapterListener");
          this.zznJ.transact(6, localParcel1, localParcel2, 0);
          localParcel2.readException();
          return;
        }
        finally
        {
          localParcel2.recycle();
          localParcel1.recycle();
        }
      }
      
      public void onAdOpened()
        throws RemoteException
      {
        Parcel localParcel1 = Parcel.obtain();
        Parcel localParcel2 = Parcel.obtain();
        try
        {
          localParcel1.writeInterfaceToken("com.google.android.gms.ads.internal.mediation.client.IMediationAdapterListener");
          this.zznJ.transact(5, localParcel1, localParcel2, 0);
          localParcel2.readException();
          return;
        }
        finally
        {
          localParcel2.recycle();
          localParcel1.recycle();
        }
      }
      
      /* Error */
      public void zza(zzep paramzzep)
        throws RemoteException
      {
        // Byte code:
        //   0: invokestatic 29	android/os/Parcel:obtain	()Landroid/os/Parcel;
        //   3: astore_2
        //   4: invokestatic 29	android/os/Parcel:obtain	()Landroid/os/Parcel;
        //   7: astore_3
        //   8: aload_2
        //   9: ldc 31
        //   11: invokevirtual 35	android/os/Parcel:writeInterfaceToken	(Ljava/lang/String;)V
        //   14: aload_1
        //   15: ifnull +45 -> 60
        //   18: aload_1
        //   19: invokeinterface 61 1 0
        //   24: astore 5
        //   26: aload_2
        //   27: aload 5
        //   29: invokevirtual 64	android/os/Parcel:writeStrongBinder	(Landroid/os/IBinder;)V
        //   32: aload_0
        //   33: getfield 18	com/google/android/gms/internal/zzeo$zza$zza:zznJ	Landroid/os/IBinder;
        //   36: bipush 7
        //   38: aload_2
        //   39: aload_3
        //   40: iconst_0
        //   41: invokeinterface 41 5 0
        //   46: pop
        //   47: aload_3
        //   48: invokevirtual 44	android/os/Parcel:readException	()V
        //   51: aload_3
        //   52: invokevirtual 47	android/os/Parcel:recycle	()V
        //   55: aload_2
        //   56: invokevirtual 47	android/os/Parcel:recycle	()V
        //   59: return
        //   60: aconst_null
        //   61: astore 5
        //   63: goto -37 -> 26
        //   66: astore 4
        //   68: aload_3
        //   69: invokevirtual 47	android/os/Parcel:recycle	()V
        //   72: aload_2
        //   73: invokevirtual 47	android/os/Parcel:recycle	()V
        //   76: aload 4
        //   78: athrow
        // Local variable table:
        //   start	length	slot	name	signature
        //   0	79	0	this	zza
        //   0	79	1	paramzzep	zzep
        //   3	70	2	localParcel1	Parcel
        //   7	62	3	localParcel2	Parcel
        //   66	11	4	localObject	Object
        //   24	38	5	localIBinder	IBinder
        // Exception table:
        //   from	to	target	type
        //   8	51	66	finally
      }
    }
  }
}


/* Location:              /Users/tjledwith/Downloads/dex2jar-0.0.9.8/classes_dex2jar.jar!/com/google/android/gms/internal/zzeo.class
 * Java compiler version: 6 (50.0)
 * JD-Core Version:       0.7.1
 */