package com.google.android.gms.internal;

import android.os.Binder;
import android.os.Bundle;
import android.os.IBinder;
import android.os.IInterface;
import android.os.Parcel;
import android.os.Parcelable.Creator;
import android.os.RemoteException;

public abstract interface zzfk
  extends IInterface
{
  public abstract void onBackPressed()
    throws RemoteException;
  
  public abstract void onCreate(Bundle paramBundle)
    throws RemoteException;
  
  public abstract void onDestroy()
    throws RemoteException;
  
  public abstract void onPause()
    throws RemoteException;
  
  public abstract void onRestart()
    throws RemoteException;
  
  public abstract void onResume()
    throws RemoteException;
  
  public abstract void onSaveInstanceState(Bundle paramBundle)
    throws RemoteException;
  
  public abstract void onStart()
    throws RemoteException;
  
  public abstract void onStop()
    throws RemoteException;
  
  public abstract void zzaE()
    throws RemoteException;
  
  public abstract boolean zzeF()
    throws RemoteException;
  
  public static abstract class zza
    extends Binder
    implements zzfk
  {
    public zza()
    {
      attachInterface(this, "com.google.android.gms.ads.internal.overlay.client.IAdOverlay");
    }
    
    public static zzfk zzL(IBinder paramIBinder)
    {
      Object localObject;
      if (paramIBinder == null) {
        localObject = null;
      }
      for (;;)
      {
        return (zzfk)localObject;
        IInterface localIInterface = paramIBinder.queryLocalInterface("com.google.android.gms.ads.internal.overlay.client.IAdOverlay");
        if ((localIInterface != null) && ((localIInterface instanceof zzfk))) {
          localObject = (zzfk)localIInterface;
        } else {
          localObject = new zza(paramIBinder);
        }
      }
    }
    
    public IBinder asBinder()
    {
      return this;
    }
    
    public boolean onTransact(int paramInt1, Parcel paramParcel1, Parcel paramParcel2, int paramInt2)
      throws RemoteException
    {
      Bundle localBundle = null;
      int i = 1;
      switch (paramInt1)
      {
      default: 
        i = super.onTransact(paramInt1, paramParcel1, paramParcel2, paramInt2);
      case 1598968902: 
      case 1: 
      case 2: 
      case 3: 
      case 4: 
      case 5: 
      case 6: 
      case 7: 
      case 8: 
      case 9: 
      case 10: 
        for (;;)
        {
          return i;
          paramParcel2.writeString("com.google.android.gms.ads.internal.overlay.client.IAdOverlay");
          continue;
          paramParcel1.enforceInterface("com.google.android.gms.ads.internal.overlay.client.IAdOverlay");
          if (paramParcel1.readInt() != 0) {
            localBundle = (Bundle)Bundle.CREATOR.createFromParcel(paramParcel1);
          }
          onCreate(localBundle);
          paramParcel2.writeNoException();
          continue;
          paramParcel1.enforceInterface("com.google.android.gms.ads.internal.overlay.client.IAdOverlay");
          onRestart();
          paramParcel2.writeNoException();
          continue;
          paramParcel1.enforceInterface("com.google.android.gms.ads.internal.overlay.client.IAdOverlay");
          onStart();
          paramParcel2.writeNoException();
          continue;
          paramParcel1.enforceInterface("com.google.android.gms.ads.internal.overlay.client.IAdOverlay");
          onResume();
          paramParcel2.writeNoException();
          continue;
          paramParcel1.enforceInterface("com.google.android.gms.ads.internal.overlay.client.IAdOverlay");
          onPause();
          paramParcel2.writeNoException();
          continue;
          paramParcel1.enforceInterface("com.google.android.gms.ads.internal.overlay.client.IAdOverlay");
          if (paramParcel1.readInt() != 0) {
            localBundle = (Bundle)Bundle.CREATOR.createFromParcel(paramParcel1);
          }
          onSaveInstanceState(localBundle);
          paramParcel2.writeNoException();
          if (localBundle != null)
          {
            paramParcel2.writeInt(i);
            localBundle.writeToParcel(paramParcel2, i);
          }
          else
          {
            paramParcel2.writeInt(0);
            continue;
            paramParcel1.enforceInterface("com.google.android.gms.ads.internal.overlay.client.IAdOverlay");
            onStop();
            paramParcel2.writeNoException();
            continue;
            paramParcel1.enforceInterface("com.google.android.gms.ads.internal.overlay.client.IAdOverlay");
            onDestroy();
            paramParcel2.writeNoException();
            continue;
            paramParcel1.enforceInterface("com.google.android.gms.ads.internal.overlay.client.IAdOverlay");
            zzaE();
            paramParcel2.writeNoException();
            continue;
            paramParcel1.enforceInterface("com.google.android.gms.ads.internal.overlay.client.IAdOverlay");
            onBackPressed();
            paramParcel2.writeNoException();
          }
        }
      }
      paramParcel1.enforceInterface("com.google.android.gms.ads.internal.overlay.client.IAdOverlay");
      boolean bool = zzeF();
      paramParcel2.writeNoException();
      if (bool) {}
      int k;
      for (int j = i;; k = 0)
      {
        paramParcel2.writeInt(j);
        break;
      }
    }
    
    private static class zza
      implements zzfk
    {
      private IBinder zznJ;
      
      zza(IBinder paramIBinder)
      {
        this.zznJ = paramIBinder;
      }
      
      public IBinder asBinder()
      {
        return this.zznJ;
      }
      
      public void onBackPressed()
        throws RemoteException
      {
        Parcel localParcel1 = Parcel.obtain();
        Parcel localParcel2 = Parcel.obtain();
        try
        {
          localParcel1.writeInterfaceToken("com.google.android.gms.ads.internal.overlay.client.IAdOverlay");
          this.zznJ.transact(10, localParcel1, localParcel2, 0);
          localParcel2.readException();
          return;
        }
        finally
        {
          localParcel2.recycle();
          localParcel1.recycle();
        }
      }
      
      /* Error */
      public void onCreate(Bundle paramBundle)
        throws RemoteException
      {
        // Byte code:
        //   0: invokestatic 29	android/os/Parcel:obtain	()Landroid/os/Parcel;
        //   3: astore_2
        //   4: invokestatic 29	android/os/Parcel:obtain	()Landroid/os/Parcel;
        //   7: astore_3
        //   8: aload_2
        //   9: ldc 31
        //   11: invokevirtual 35	android/os/Parcel:writeInterfaceToken	(Ljava/lang/String;)V
        //   14: aload_1
        //   15: ifnull +41 -> 56
        //   18: aload_2
        //   19: iconst_1
        //   20: invokevirtual 53	android/os/Parcel:writeInt	(I)V
        //   23: aload_1
        //   24: aload_2
        //   25: iconst_0
        //   26: invokevirtual 59	android/os/Bundle:writeToParcel	(Landroid/os/Parcel;I)V
        //   29: aload_0
        //   30: getfield 18	com/google/android/gms/internal/zzfk$zza$zza:zznJ	Landroid/os/IBinder;
        //   33: iconst_1
        //   34: aload_2
        //   35: aload_3
        //   36: iconst_0
        //   37: invokeinterface 41 5 0
        //   42: pop
        //   43: aload_3
        //   44: invokevirtual 44	android/os/Parcel:readException	()V
        //   47: aload_3
        //   48: invokevirtual 47	android/os/Parcel:recycle	()V
        //   51: aload_2
        //   52: invokevirtual 47	android/os/Parcel:recycle	()V
        //   55: return
        //   56: aload_2
        //   57: iconst_0
        //   58: invokevirtual 53	android/os/Parcel:writeInt	(I)V
        //   61: goto -32 -> 29
        //   64: astore 4
        //   66: aload_3
        //   67: invokevirtual 47	android/os/Parcel:recycle	()V
        //   70: aload_2
        //   71: invokevirtual 47	android/os/Parcel:recycle	()V
        //   74: aload 4
        //   76: athrow
        // Local variable table:
        //   start	length	slot	name	signature
        //   0	77	0	this	zza
        //   0	77	1	paramBundle	Bundle
        //   3	68	2	localParcel1	Parcel
        //   7	60	3	localParcel2	Parcel
        //   64	11	4	localObject	Object
        // Exception table:
        //   from	to	target	type
        //   8	47	64	finally
        //   56	61	64	finally
      }
      
      public void onDestroy()
        throws RemoteException
      {
        Parcel localParcel1 = Parcel.obtain();
        Parcel localParcel2 = Parcel.obtain();
        try
        {
          localParcel1.writeInterfaceToken("com.google.android.gms.ads.internal.overlay.client.IAdOverlay");
          this.zznJ.transact(8, localParcel1, localParcel2, 0);
          localParcel2.readException();
          return;
        }
        finally
        {
          localParcel2.recycle();
          localParcel1.recycle();
        }
      }
      
      public void onPause()
        throws RemoteException
      {
        Parcel localParcel1 = Parcel.obtain();
        Parcel localParcel2 = Parcel.obtain();
        try
        {
          localParcel1.writeInterfaceToken("com.google.android.gms.ads.internal.overlay.client.IAdOverlay");
          this.zznJ.transact(5, localParcel1, localParcel2, 0);
          localParcel2.readException();
          return;
        }
        finally
        {
          localParcel2.recycle();
          localParcel1.recycle();
        }
      }
      
      public void onRestart()
        throws RemoteException
      {
        Parcel localParcel1 = Parcel.obtain();
        Parcel localParcel2 = Parcel.obtain();
        try
        {
          localParcel1.writeInterfaceToken("com.google.android.gms.ads.internal.overlay.client.IAdOverlay");
          this.zznJ.transact(2, localParcel1, localParcel2, 0);
          localParcel2.readException();
          return;
        }
        finally
        {
          localParcel2.recycle();
          localParcel1.recycle();
        }
      }
      
      public void onResume()
        throws RemoteException
      {
        Parcel localParcel1 = Parcel.obtain();
        Parcel localParcel2 = Parcel.obtain();
        try
        {
          localParcel1.writeInterfaceToken("com.google.android.gms.ads.internal.overlay.client.IAdOverlay");
          this.zznJ.transact(4, localParcel1, localParcel2, 0);
          localParcel2.readException();
          return;
        }
        finally
        {
          localParcel2.recycle();
          localParcel1.recycle();
        }
      }
      
      /* Error */
      public void onSaveInstanceState(Bundle paramBundle)
        throws RemoteException
      {
        // Byte code:
        //   0: invokestatic 29	android/os/Parcel:obtain	()Landroid/os/Parcel;
        //   3: astore_2
        //   4: invokestatic 29	android/os/Parcel:obtain	()Landroid/os/Parcel;
        //   7: astore_3
        //   8: aload_2
        //   9: ldc 31
        //   11: invokevirtual 35	android/os/Parcel:writeInterfaceToken	(Ljava/lang/String;)V
        //   14: aload_1
        //   15: ifnull +54 -> 69
        //   18: aload_2
        //   19: iconst_1
        //   20: invokevirtual 53	android/os/Parcel:writeInt	(I)V
        //   23: aload_1
        //   24: aload_2
        //   25: iconst_0
        //   26: invokevirtual 59	android/os/Bundle:writeToParcel	(Landroid/os/Parcel;I)V
        //   29: aload_0
        //   30: getfield 18	com/google/android/gms/internal/zzfk$zza$zza:zznJ	Landroid/os/IBinder;
        //   33: bipush 6
        //   35: aload_2
        //   36: aload_3
        //   37: iconst_0
        //   38: invokeinterface 41 5 0
        //   43: pop
        //   44: aload_3
        //   45: invokevirtual 44	android/os/Parcel:readException	()V
        //   48: aload_3
        //   49: invokevirtual 68	android/os/Parcel:readInt	()I
        //   52: ifeq +8 -> 60
        //   55: aload_1
        //   56: aload_3
        //   57: invokevirtual 72	android/os/Bundle:readFromParcel	(Landroid/os/Parcel;)V
        //   60: aload_3
        //   61: invokevirtual 47	android/os/Parcel:recycle	()V
        //   64: aload_2
        //   65: invokevirtual 47	android/os/Parcel:recycle	()V
        //   68: return
        //   69: aload_2
        //   70: iconst_0
        //   71: invokevirtual 53	android/os/Parcel:writeInt	(I)V
        //   74: goto -45 -> 29
        //   77: astore 4
        //   79: aload_3
        //   80: invokevirtual 47	android/os/Parcel:recycle	()V
        //   83: aload_2
        //   84: invokevirtual 47	android/os/Parcel:recycle	()V
        //   87: aload 4
        //   89: athrow
        // Local variable table:
        //   start	length	slot	name	signature
        //   0	90	0	this	zza
        //   0	90	1	paramBundle	Bundle
        //   3	81	2	localParcel1	Parcel
        //   7	73	3	localParcel2	Parcel
        //   77	11	4	localObject	Object
        // Exception table:
        //   from	to	target	type
        //   8	60	77	finally
        //   69	74	77	finally
      }
      
      public void onStart()
        throws RemoteException
      {
        Parcel localParcel1 = Parcel.obtain();
        Parcel localParcel2 = Parcel.obtain();
        try
        {
          localParcel1.writeInterfaceToken("com.google.android.gms.ads.internal.overlay.client.IAdOverlay");
          this.zznJ.transact(3, localParcel1, localParcel2, 0);
          localParcel2.readException();
          return;
        }
        finally
        {
          localParcel2.recycle();
          localParcel1.recycle();
        }
      }
      
      public void onStop()
        throws RemoteException
      {
        Parcel localParcel1 = Parcel.obtain();
        Parcel localParcel2 = Parcel.obtain();
        try
        {
          localParcel1.writeInterfaceToken("com.google.android.gms.ads.internal.overlay.client.IAdOverlay");
          this.zznJ.transact(7, localParcel1, localParcel2, 0);
          localParcel2.readException();
          return;
        }
        finally
        {
          localParcel2.recycle();
          localParcel1.recycle();
        }
      }
      
      public void zzaE()
        throws RemoteException
      {
        Parcel localParcel1 = Parcel.obtain();
        Parcel localParcel2 = Parcel.obtain();
        try
        {
          localParcel1.writeInterfaceToken("com.google.android.gms.ads.internal.overlay.client.IAdOverlay");
          this.zznJ.transact(9, localParcel1, localParcel2, 0);
          localParcel2.readException();
          return;
        }
        finally
        {
          localParcel2.recycle();
          localParcel1.recycle();
        }
      }
      
      public boolean zzeF()
        throws RemoteException
      {
        boolean bool = false;
        Parcel localParcel1 = Parcel.obtain();
        Parcel localParcel2 = Parcel.obtain();
        try
        {
          localParcel1.writeInterfaceToken("com.google.android.gms.ads.internal.overlay.client.IAdOverlay");
          this.zznJ.transact(11, localParcel1, localParcel2, 0);
          localParcel2.readException();
          int i = localParcel2.readInt();
          if (i != 0) {
            bool = true;
          }
          return bool;
        }
        finally
        {
          localParcel2.recycle();
          localParcel1.recycle();
        }
      }
    }
  }
}


/* Location:              /Users/tjledwith/Downloads/dex2jar-0.0.9.8/classes_dex2jar.jar!/com/google/android/gms/internal/zzfk.class
 * Java compiler version: 6 (50.0)
 * JD-Core Version:       0.7.1
 */