package com.google.android.gms.ads.internal.request;

import android.os.Binder;
import android.os.IBinder;
import android.os.IInterface;
import android.os.Parcel;
import android.os.RemoteException;

public abstract interface zzk
  extends IInterface
{
  public abstract void zzb(AdResponseParcel paramAdResponseParcel)
    throws RemoteException;
  
  public static abstract class zza
    extends Binder
    implements zzk
  {
    public zza()
    {
      attachInterface(this, "com.google.android.gms.ads.internal.request.IAdResponseListener");
    }
    
    public static zzk zzY(IBinder paramIBinder)
    {
      Object localObject;
      if (paramIBinder == null) {
        localObject = null;
      }
      for (;;)
      {
        return (zzk)localObject;
        IInterface localIInterface = paramIBinder.queryLocalInterface("com.google.android.gms.ads.internal.request.IAdResponseListener");
        if ((localIInterface != null) && ((localIInterface instanceof zzk))) {
          localObject = (zzk)localIInterface;
        } else {
          localObject = new zza(paramIBinder);
        }
      }
    }
    
    public IBinder asBinder()
    {
      return this;
    }
    
    public boolean onTransact(int paramInt1, Parcel paramParcel1, Parcel paramParcel2, int paramInt2)
      throws RemoteException
    {
      boolean bool;
      switch (paramInt1)
      {
      default: 
      case 1598968902: 
        for (bool = super.onTransact(paramInt1, paramParcel1, paramParcel2, paramInt2);; bool = true)
        {
          return bool;
          paramParcel2.writeString("com.google.android.gms.ads.internal.request.IAdResponseListener");
        }
      }
      paramParcel1.enforceInterface("com.google.android.gms.ads.internal.request.IAdResponseListener");
      if (paramParcel1.readInt() != 0) {}
      for (AdResponseParcel localAdResponseParcel = AdResponseParcel.CREATOR.zzj(paramParcel1);; localAdResponseParcel = null)
      {
        zzb(localAdResponseParcel);
        paramParcel2.writeNoException();
        bool = true;
        break;
      }
    }
    
    private static class zza
      implements zzk
    {
      private IBinder zznJ;
      
      zza(IBinder paramIBinder)
      {
        this.zznJ = paramIBinder;
      }
      
      public IBinder asBinder()
      {
        return this.zznJ;
      }
      
      /* Error */
      public void zzb(AdResponseParcel paramAdResponseParcel)
        throws RemoteException
      {
        // Byte code:
        //   0: invokestatic 30	android/os/Parcel:obtain	()Landroid/os/Parcel;
        //   3: astore_2
        //   4: invokestatic 30	android/os/Parcel:obtain	()Landroid/os/Parcel;
        //   7: astore_3
        //   8: aload_2
        //   9: ldc 32
        //   11: invokevirtual 36	android/os/Parcel:writeInterfaceToken	(Ljava/lang/String;)V
        //   14: aload_1
        //   15: ifnull +41 -> 56
        //   18: aload_2
        //   19: iconst_1
        //   20: invokevirtual 40	android/os/Parcel:writeInt	(I)V
        //   23: aload_1
        //   24: aload_2
        //   25: iconst_0
        //   26: invokevirtual 46	com/google/android/gms/ads/internal/request/AdResponseParcel:writeToParcel	(Landroid/os/Parcel;I)V
        //   29: aload_0
        //   30: getfield 18	com/google/android/gms/ads/internal/request/zzk$zza$zza:zznJ	Landroid/os/IBinder;
        //   33: iconst_1
        //   34: aload_2
        //   35: aload_3
        //   36: iconst_0
        //   37: invokeinterface 52 5 0
        //   42: pop
        //   43: aload_3
        //   44: invokevirtual 55	android/os/Parcel:readException	()V
        //   47: aload_3
        //   48: invokevirtual 58	android/os/Parcel:recycle	()V
        //   51: aload_2
        //   52: invokevirtual 58	android/os/Parcel:recycle	()V
        //   55: return
        //   56: aload_2
        //   57: iconst_0
        //   58: invokevirtual 40	android/os/Parcel:writeInt	(I)V
        //   61: goto -32 -> 29
        //   64: astore 4
        //   66: aload_3
        //   67: invokevirtual 58	android/os/Parcel:recycle	()V
        //   70: aload_2
        //   71: invokevirtual 58	android/os/Parcel:recycle	()V
        //   74: aload 4
        //   76: athrow
        // Local variable table:
        //   start	length	slot	name	signature
        //   0	77	0	this	zza
        //   0	77	1	paramAdResponseParcel	AdResponseParcel
        //   3	68	2	localParcel1	Parcel
        //   7	60	3	localParcel2	Parcel
        //   64	11	4	localObject	Object
        // Exception table:
        //   from	to	target	type
        //   8	47	64	finally
        //   56	61	64	finally
      }
    }
  }
}


/* Location:              /Users/tjledwith/Downloads/dex2jar-0.0.9.8/classes_dex2jar.jar!/com/google/android/gms/ads/internal/request/zzk.class
 * Java compiler version: 6 (50.0)
 * JD-Core Version:       0.7.1
 */