package crittercism.android;

public final class dj
  extends di
{
  private cw a;
  private dc b;
  private boolean c;
  private cy d;
  
  public dj(cw paramcw, dc paramdc, cy paramcy)
  {
    this(paramcw, paramdc, false, paramcy);
  }
  
  public dj(cw paramcw, dc paramdc, boolean paramBoolean, cy paramcy)
  {
    this.a = paramcw;
    this.b = paramdc;
    this.c = paramBoolean;
    this.d = paramcy;
  }
  
  /* Error */
  public final void a()
  {
    // Byte code:
    //   0: aconst_null
    //   1: astore_1
    //   2: aload_0
    //   3: getfield 24	crittercism/android/dj:b	Lcrittercism/android/dc;
    //   6: invokevirtual 43	crittercism/android/dc:a	()Ljava/net/HttpURLConnection;
    //   9: astore 4
    //   11: aload 4
    //   13: ifnonnull +4 -> 17
    //   16: return
    //   17: aload_0
    //   18: getfield 22	crittercism/android/dj:a	Lcrittercism/android/cw;
    //   21: aload 4
    //   23: invokevirtual 49	java/net/HttpURLConnection:getOutputStream	()Ljava/io/OutputStream;
    //   26: invokeinterface 54 2 0
    //   31: aload 4
    //   33: invokevirtual 58	java/net/HttpURLConnection:getResponseCode	()I
    //   36: istore 21
    //   38: aload_0
    //   39: getfield 26	crittercism/android/dj:c	Z
    //   42: ifeq +338 -> 380
    //   45: new 60	java/lang/StringBuilder
    //   48: dup
    //   49: invokespecial 61	java/lang/StringBuilder:<init>	()V
    //   52: astore 25
    //   54: new 63	java/io/BufferedReader
    //   57: dup
    //   58: new 65	java/io/InputStreamReader
    //   61: dup
    //   62: aload 4
    //   64: invokevirtual 71	java/net/URLConnection:getInputStream	()Ljava/io/InputStream;
    //   67: invokespecial 74	java/io/InputStreamReader:<init>	(Ljava/io/InputStream;)V
    //   70: invokespecial 77	java/io/BufferedReader:<init>	(Ljava/io/Reader;)V
    //   73: astore 26
    //   75: aload 26
    //   77: invokevirtual 80	java/io/BufferedReader:read	()I
    //   80: istore 27
    //   82: iload 27
    //   84: bipush -1
    //   86: if_icmpeq +85 -> 171
    //   89: aload 25
    //   91: iload 27
    //   93: i2c
    //   94: invokevirtual 84	java/lang/StringBuilder:append	(C)Ljava/lang/StringBuilder;
    //   97: pop
    //   98: goto -23 -> 75
    //   101: astore 24
    //   103: iload 21
    //   105: istore 7
    //   107: aload 24
    //   109: astore 6
    //   111: new 60	java/lang/StringBuilder
    //   114: dup
    //   115: ldc 86
    //   117: invokespecial 89	java/lang/StringBuilder:<init>	(Ljava/lang/String;)V
    //   120: aload 6
    //   122: invokevirtual 93	java/io/UnsupportedEncodingException:getMessage	()Ljava/lang/String;
    //   125: invokevirtual 96	java/lang/StringBuilder:append	(Ljava/lang/String;)Ljava/lang/StringBuilder;
    //   128: pop
    //   129: invokestatic 100	crittercism/android/dx:b	()V
    //   132: invokestatic 102	crittercism/android/dx:c	()V
    //   135: iload 7
    //   137: istore 9
    //   139: iconst_0
    //   140: istore 10
    //   142: aload 4
    //   144: invokevirtual 105	java/net/HttpURLConnection:disconnect	()V
    //   147: aload_0
    //   148: getfield 28	crittercism/android/dj:d	Lcrittercism/android/cy;
    //   151: ifnull -135 -> 16
    //   154: aload_0
    //   155: getfield 28	crittercism/android/dj:d	Lcrittercism/android/cy;
    //   158: iload 10
    //   160: iload 9
    //   162: aload_1
    //   163: invokeinterface 110 4 0
    //   168: goto -152 -> 16
    //   171: aload 26
    //   173: invokevirtual 113	java/io/BufferedReader:close	()V
    //   176: new 115	org/json/JSONObject
    //   179: dup
    //   180: aload 25
    //   182: invokevirtual 118	java/lang/StringBuilder:toString	()Ljava/lang/String;
    //   185: invokespecial 119	org/json/JSONObject:<init>	(Ljava/lang/String;)V
    //   188: astore 28
    //   190: aload 28
    //   192: astore_1
    //   193: iconst_0
    //   194: istore 10
    //   196: iload 21
    //   198: istore 9
    //   200: goto -58 -> 142
    //   203: astore 19
    //   205: bipush -1
    //   207: istore 9
    //   209: new 60	java/lang/StringBuilder
    //   212: dup
    //   213: ldc 121
    //   215: invokespecial 89	java/lang/StringBuilder:<init>	(Ljava/lang/String;)V
    //   218: aload 19
    //   220: invokevirtual 122	java/net/SocketTimeoutException:getMessage	()Ljava/lang/String;
    //   223: invokevirtual 96	java/lang/StringBuilder:append	(Ljava/lang/String;)Ljava/lang/StringBuilder;
    //   226: pop
    //   227: invokestatic 100	crittercism/android/dx:b	()V
    //   230: iconst_1
    //   231: istore 10
    //   233: goto -91 -> 142
    //   236: astore 15
    //   238: aload 15
    //   240: astore 16
    //   242: bipush -1
    //   244: istore 17
    //   246: new 60	java/lang/StringBuilder
    //   249: dup
    //   250: ldc 124
    //   252: invokespecial 89	java/lang/StringBuilder:<init>	(Ljava/lang/String;)V
    //   255: aload 16
    //   257: invokevirtual 125	java/io/IOException:getMessage	()Ljava/lang/String;
    //   260: invokevirtual 96	java/lang/StringBuilder:append	(Ljava/lang/String;)Ljava/lang/StringBuilder;
    //   263: pop
    //   264: invokestatic 100	crittercism/android/dx:b	()V
    //   267: invokestatic 102	crittercism/android/dx:c	()V
    //   270: iload 17
    //   272: istore 9
    //   274: iconst_0
    //   275: istore 10
    //   277: goto -135 -> 142
    //   280: astore 11
    //   282: aload 11
    //   284: astore 12
    //   286: bipush -1
    //   288: istore 13
    //   290: new 60	java/lang/StringBuilder
    //   293: dup
    //   294: ldc 127
    //   296: invokespecial 89	java/lang/StringBuilder:<init>	(Ljava/lang/String;)V
    //   299: aload 12
    //   301: invokevirtual 128	org/json/JSONException:getMessage	()Ljava/lang/String;
    //   304: invokevirtual 96	java/lang/StringBuilder:append	(Ljava/lang/String;)Ljava/lang/StringBuilder;
    //   307: pop
    //   308: invokestatic 100	crittercism/android/dx:b	()V
    //   311: iload 13
    //   313: istore 9
    //   315: iconst_0
    //   316: istore 10
    //   318: invokestatic 102	crittercism/android/dx:c	()V
    //   321: goto -179 -> 142
    //   324: astore 23
    //   326: iload 21
    //   328: istore 13
    //   330: aload 23
    //   332: astore 12
    //   334: goto -44 -> 290
    //   337: astore 22
    //   339: iload 21
    //   341: istore 17
    //   343: aload 22
    //   345: astore 16
    //   347: goto -101 -> 246
    //   350: astore 19
    //   352: iload 21
    //   354: istore 9
    //   356: goto -147 -> 209
    //   359: astore 5
    //   361: aload 5
    //   363: astore 6
    //   365: bipush -1
    //   367: istore 7
    //   369: goto -258 -> 111
    //   372: astore_3
    //   373: goto -357 -> 16
    //   376: astore_2
    //   377: goto -361 -> 16
    //   380: aconst_null
    //   381: astore 28
    //   383: goto -193 -> 190
    // Local variable table:
    //   start	length	slot	name	signature
    //   0	386	0	this	dj
    //   1	192	1	localObject1	Object
    //   376	1	2	localIOException1	java.io.IOException
    //   372	1	3	localGeneralSecurityException	java.security.GeneralSecurityException
    //   9	134	4	localHttpURLConnection	java.net.HttpURLConnection
    //   359	3	5	localUnsupportedEncodingException1	java.io.UnsupportedEncodingException
    //   109	255	6	localObject2	Object
    //   105	263	7	i	int
    //   137	218	9	j	int
    //   140	177	10	bool	boolean
    //   280	3	11	localJSONException1	org.json.JSONException
    //   284	49	12	localObject3	Object
    //   288	41	13	k	int
    //   236	3	15	localIOException2	java.io.IOException
    //   240	106	16	localObject4	Object
    //   244	98	17	m	int
    //   203	16	19	localSocketTimeoutException1	java.net.SocketTimeoutException
    //   350	1	19	localSocketTimeoutException2	java.net.SocketTimeoutException
    //   36	317	21	n	int
    //   337	7	22	localIOException3	java.io.IOException
    //   324	7	23	localJSONException2	org.json.JSONException
    //   101	7	24	localUnsupportedEncodingException2	java.io.UnsupportedEncodingException
    //   52	129	25	localStringBuilder	StringBuilder
    //   73	99	26	localBufferedReader	java.io.BufferedReader
    //   80	12	27	i1	int
    //   188	194	28	localJSONObject	org.json.JSONObject
    // Exception table:
    //   from	to	target	type
    //   38	98	101	java/io/UnsupportedEncodingException
    //   171	190	101	java/io/UnsupportedEncodingException
    //   17	38	203	java/net/SocketTimeoutException
    //   17	38	236	java/io/IOException
    //   17	38	280	org/json/JSONException
    //   38	98	324	org/json/JSONException
    //   171	190	324	org/json/JSONException
    //   38	98	337	java/io/IOException
    //   171	190	337	java/io/IOException
    //   38	98	350	java/net/SocketTimeoutException
    //   171	190	350	java/net/SocketTimeoutException
    //   17	38	359	java/io/UnsupportedEncodingException
    //   2	11	372	java/security/GeneralSecurityException
    //   2	11	376	java/io/IOException
  }
}


/* Location:              /Users/tjledwith/Downloads/dex2jar-0.0.9.8/classes_dex2jar.jar!/crittercism/android/dj.class
 * Java compiler version: 6 (50.0)
 * JD-Core Version:       0.7.1
 */